<?xml version="1.0"?><!--Scan file created using MSXML 6.0.--><Layer>
<Header>
	<AmericaMakesSchemaVersion>2020-03-23</AmericaMakesSchemaVersion>
	<LayerNum>348</LayerNum>
	<LayerThickness>0.1</LayerThickness>
	<AbsoluteHeight>34.800000000000004</AbsoluteHeight>
	<DosingFactor>1.75</DosingFactor>
	<BuildDescription>Placeholder</BuildDescription></Header>
<VelocityProfileList>
	<VelocityProfile><ID>1</ID>
		<Velocity>3000</Velocity><Mode>Auto</Mode>
		<LaserOnDelay>300</LaserOnDelay><LaserOffDelay>300</LaserOffDelay><JumpDelay>0</JumpDelay>
		<MarkDelay>0</MarkDelay><PolygonDelay>0</PolygonDelay></VelocityProfile>
	<VelocityProfile><ID>2</ID>
		<Velocity>800</Velocity><Mode>Auto</Mode>
		<LaserOnDelay>300</LaserOnDelay><LaserOffDelay>300</LaserOffDelay><JumpDelay>0</JumpDelay>
		<MarkDelay>0</MarkDelay><PolygonDelay>0</PolygonDelay></VelocityProfile>
	<VelocityProfile><ID>3</ID>
		<Velocity>1000</Velocity><Mode>Auto</Mode>
		<LaserOnDelay>300</LaserOnDelay><LaserOffDelay>300</LaserOffDelay><JumpDelay>0</JumpDelay>
		<MarkDelay>0</MarkDelay><PolygonDelay>0</PolygonDelay></VelocityProfile>
	<VelocityProfile><ID>4</ID>
		<Velocity>3000</Velocity><Mode>Auto</Mode>
		<LaserOnDelay>300</LaserOnDelay><LaserOffDelay>300</LaserOffDelay><JumpDelay>0</JumpDelay>
		<MarkDelay>0</MarkDelay><PolygonDelay>0</PolygonDelay></VelocityProfile></VelocityProfileList>
<SegmentStyleList>
	<SegmentStyle><ID>1</ID>
		<VelocityProfileID>2</VelocityProfileID><LaserMode>Independent</LaserMode>
		<Traveler><ID>1</ID>
			<SyncDelay>0</SyncDelay><Power>180</Power><SpotSize>75</SpotSize></Traveler></SegmentStyle>
	<SegmentStyle><ID>2</ID>
		<VelocityProfileID>3</VelocityProfileID><LaserMode>Independent</LaserMode>
		<Traveler><ID>2</ID>
			<SyncDelay>0</SyncDelay><Power>200</Power><SpotSize>75</SpotSize></Traveler></SegmentStyle>
	<SegmentStyle><ID>3</ID>
		<VelocityProfileID>2</VelocityProfileID><LaserMode>Independent</LaserMode>
		<Traveler><ID>1</ID>
			<SyncDelay>0</SyncDelay><Power>350</Power><SpotSize>125</SpotSize></Traveler></SegmentStyle>
	<SegmentStyle><ID>4</ID>
		<VelocityProfileID>3</VelocityProfileID><LaserMode>Independent</LaserMode>
		<Traveler><ID>2</ID>
			<SyncDelay>0</SyncDelay><Power>375</Power><SpotSize>125</SpotSize></Traveler></SegmentStyle>
	<SegmentStyle><ID>5</ID>
		<VelocityProfileID>1</VelocityProfileID></SegmentStyle>
	<SegmentStyle><ID>6</ID>
		<VelocityProfileID>1</VelocityProfileID></SegmentStyle>
	<SegmentStyle><ID>7</ID>
		<VelocityProfileID>4</VelocityProfileID></SegmentStyle>
	<SegmentStyle><ID>8</ID>
		<VelocityProfileID>4</VelocityProfileID></SegmentStyle></SegmentStyleList>
<TrajectoryList>
<Trajectory>
	<TrajectoryID>9998</TrajectoryID>
	<PathProcessingMode>sequential</PathProcessingMode>
	<Path>
		<Type>contour</Type>
		<Tag>column</Tag>
		<NumSegments>5</NumSegments>
		<SkyWritingMode>0</SkyWritingMode>
		<Start><X>-15.050</X><Y>-21.333</Y></Start>
		<Segment><SegStyle>1</SegStyle><End><X>-21.333</X><Y>-15.050</Y></End></Segment>
		<Segment><SegStyle>1</SegStyle><End><X>-29.950</X><Y>-15.050</Y></End></Segment>
		<Segment><SegStyle>1</SegStyle><End><X>-29.950</X><Y>-29.950</Y></End></Segment>
		<Segment><SegStyle>1</SegStyle><End><X>-15.050</X><Y>-29.950</Y></End></Segment>
		<Segment><SegStyle>1</SegStyle><End><X>-15.050</X><Y>-21.333</Y></End></Segment></Path>
	<Path>
		<Type>contour</Type>
		<Tag>pyramid</Tag>
		<NumSegments>4</NumSegments>
		<SkyWritingMode>1</SkyWritingMode>
		<Start><X>-14.544</X><Y>45.456</Y></Start>
		<Segment><SegStyle>2</SegStyle><End><X>-29.935</X><Y>45.456</Y></End></Segment>
		<Segment><SegStyle>2</SegStyle><End><X>-29.935</X><Y>30.065</Y></End></Segment>
		<Segment><SegStyle>2</SegStyle><End><X>-14.544</X><Y>30.065</Y></End></Segment>
		<Segment><SegStyle>2</SegStyle><End><X>-14.544</X><Y>45.456</Y></End></Segment></Path>
	<Path>
		<Type>contour</Type>
		<Tag>pyramid</Tag>
		<NumSegments>4</NumSegments>
		<SkyWritingMode>1</SkyWritingMode>
		<Start><X>-14.609</X><Y>45.391</Y></Start>
		<Segment><SegStyle>2</SegStyle><End><X>-29.870</X><Y>45.391</Y></End></Segment>
		<Segment><SegStyle>2</SegStyle><End><X>-29.870</X><Y>30.130</Y></End></Segment>
		<Segment><SegStyle>2</SegStyle><End><X>-14.609</X><Y>30.130</Y></End></Segment>
		<Segment><SegStyle>2</SegStyle><End><X>-14.609</X><Y>45.391</Y></End></Segment></Path></Trajectory>
<Trajectory>
	<TrajectoryID>9999</TrajectoryID>
	<PathProcessingMode>sequential</PathProcessingMode>
	<Path>
		<Type>hatch</Type>
		<Tag>column</Tag>
		<NumSegments>537</NumSegments>
		<SkyWritingMode>0</SkyWritingMode>
		<Start><X>-15.057</X><Y>-29.950</Y></Start>
		<Segment><SegStyle>3</SegStyle><End><X>-15.050</X><Y>-29.927</Y></End></Segment>
		<Segment><SegStyle>5</SegStyle><End><X>-15.050</X><Y>-29.701</Y></End></Segment>
		<Segment><SegStyle>3</SegStyle><End><X>-15.131</X><Y>-29.950</Y></End></Segment>
		<Segment><SegStyle>5</SegStyle><End><X>-15.205</X><Y>-29.950</Y></End></Segment>
		<Segment><SegStyle>3</SegStyle><End><X>-15.050</X><Y>-29.474</Y></End></Segment>
		<Segment><SegStyle>5</SegStyle><End><X>-15.050</X><Y>-29.248</Y></End></Segment>
		<Segment><SegStyle>3</SegStyle><End><X>-15.278</X><Y>-29.950</Y></End></Segment>
		<Segment><SegStyle>5</SegStyle><End><X>-15.352</X><Y>-29.950</Y></End></Segment>
		<Segment><SegStyle>3</SegStyle><End><X>-15.050</X><Y>-29.021</Y></End></Segment>
		<Segment><SegStyle>5</SegStyle><End><X>-15.050</X><Y>-28.795</Y></End></Segment>
		<Segment><SegStyle>3</SegStyle><End><X>-15.425</X><Y>-29.950</Y></End></Segment>
		<Segment><SegStyle>5</SegStyle><End><X>-15.499</X><Y>-29.950</Y></End></Segment>
		<Segment><SegStyle>3</SegStyle><End><X>-15.050</X><Y>-28.568</Y></End></Segment>
		<Segment><SegStyle>5</SegStyle><End><X>-15.050</X><Y>-28.342</Y></End></Segment>
		<Segment><SegStyle>3</SegStyle><End><X>-15.573</X><Y>-29.950</Y></End></Segment>
		<Segment><SegStyle>5</SegStyle><End><X>-15.646</X><Y>-29.950</Y></End></Segment>
		<Segment><SegStyle>3</SegStyle><End><X>-15.050</X><Y>-28.115</Y></End></Segment>
		<Segment><SegStyle>5</SegStyle><End><X>-15.050</X><Y>-27.889</Y></End></Segment>
		<Segment><SegStyle>3</SegStyle><End><X>-15.720</X><Y>-29.950</Y></End></Segment>
		<Segment><SegStyle>5</SegStyle><End><X>-15.793</X><Y>-29.950</Y></End></Segment>
		<Segment><SegStyle>3</SegStyle><End><X>-15.050</X><Y>-27.662</Y></End></Segment>
		<Segment><SegStyle>5</SegStyle><End><X>-15.050</X><Y>-27.436</Y></End></Segment>
		<Segment><SegStyle>3</SegStyle><End><X>-15.867</X><Y>-29.950</Y></End></Segment>
		<Segment><SegStyle>5</SegStyle><End><X>-15.941</X><Y>-29.950</Y></End></Segment>
		<Segment><SegStyle>3</SegStyle><End><X>-15.050</X><Y>-27.209</Y></End></Segment>
		<Segment><SegStyle>5</SegStyle><End><X>-15.050</X><Y>-26.983</Y></End></Segment>
		<Segment><SegStyle>3</SegStyle><End><X>-16.014</X><Y>-29.950</Y></End></Segment>
		<Segment><SegStyle>5</SegStyle><End><X>-16.088</X><Y>-29.950</Y></End></Segment>
		<Segment><SegStyle>3</SegStyle><End><X>-15.050</X><Y>-26.756</Y></End></Segment>
		<Segment><SegStyle>5</SegStyle><End><X>-15.050</X><Y>-26.529</Y></End></Segment>
		<Segment><SegStyle>3</SegStyle><End><X>-16.161</X><Y>-29.950</Y></End></Segment>
		<Segment><SegStyle>5</SegStyle><End><X>-16.235</X><Y>-29.950</Y></End></Segment>
		<Segment><SegStyle>3</SegStyle><End><X>-15.050</X><Y>-26.303</Y></End></Segment>
		<Segment><SegStyle>5</SegStyle><End><X>-15.050</X><Y>-26.076</Y></End></Segment>
		<Segment><SegStyle>3</SegStyle><End><X>-16.309</X><Y>-29.950</Y></End></Segment>
		<Segment><SegStyle>5</SegStyle><End><X>-16.382</X><Y>-29.950</Y></End></Segment>
		<Segment><SegStyle>3</SegStyle><End><X>-15.050</X><Y>-25.850</Y></End></Segment>
		<Segment><SegStyle>5</SegStyle><End><X>-15.050</X><Y>-25.623</Y></End></Segment>
		<Segment><SegStyle>3</SegStyle><End><X>-16.456</X><Y>-29.950</Y></End></Segment>
		<Segment><SegStyle>5</SegStyle><End><X>-16.529</X><Y>-29.950</Y></End></Segment>
		<Segment><SegStyle>3</SegStyle><End><X>-15.050</X><Y>-25.397</Y></End></Segment>
		<Segment><SegStyle>5</SegStyle><End><X>-15.050</X><Y>-25.170</Y></End></Segment>
		<Segment><SegStyle>3</SegStyle><End><X>-16.603</X><Y>-29.950</Y></End></Segment>
		<Segment><SegStyle>5</SegStyle><End><X>-16.677</X><Y>-29.950</Y></End></Segment>
		<Segment><SegStyle>3</SegStyle><End><X>-15.050</X><Y>-24.944</Y></End></Segment>
		<Segment><SegStyle>5</SegStyle><End><X>-15.050</X><Y>-24.717</Y></End></Segment>
		<Segment><SegStyle>3</SegStyle><End><X>-16.750</X><Y>-29.950</Y></End></Segment>
		<Segment><SegStyle>5</SegStyle><End><X>-16.824</X><Y>-29.950</Y></End></Segment>
		<Segment><SegStyle>3</SegStyle><End><X>-15.050</X><Y>-24.491</Y></End></Segment>
		<Segment><SegStyle>5</SegStyle><End><X>-15.050</X><Y>-24.264</Y></End></Segment>
		<Segment><SegStyle>3</SegStyle><End><X>-16.897</X><Y>-29.950</Y></End></Segment>
		<Segment><SegStyle>5</SegStyle><End><X>-16.971</X><Y>-29.950</Y></End></Segment>
		<Segment><SegStyle>3</SegStyle><End><X>-15.050</X><Y>-24.038</Y></End></Segment>
		<Segment><SegStyle>5</SegStyle><End><X>-15.050</X><Y>-23.811</Y></End></Segment>
		<Segment><SegStyle>3</SegStyle><End><X>-17.045</X><Y>-29.950</Y></End></Segment>
		<Segment><SegStyle>5</SegStyle><End><X>-17.118</X><Y>-29.950</Y></End></Segment>
		<Segment><SegStyle>3</SegStyle><End><X>-15.050</X><Y>-23.585</Y></End></Segment>
		<Segment><SegStyle>5</SegStyle><End><X>-15.050</X><Y>-23.358</Y></End></Segment>
		<Segment><SegStyle>3</SegStyle><End><X>-17.192</X><Y>-29.950</Y></End></Segment>
		<Segment><SegStyle>5</SegStyle><End><X>-17.265</X><Y>-29.950</Y></End></Segment>
		<Segment><SegStyle>3</SegStyle><End><X>-15.050</X><Y>-23.132</Y></End></Segment>
		<Segment><SegStyle>5</SegStyle><End><X>-15.050</X><Y>-22.905</Y></End></Segment>
		<Segment><SegStyle>3</SegStyle><End><X>-17.339</X><Y>-29.950</Y></End></Segment>
		<Segment><SegStyle>5</SegStyle><End><X>-17.413</X><Y>-29.950</Y></End></Segment>
		<Segment><SegStyle>3</SegStyle><End><X>-15.050</X><Y>-22.679</Y></End></Segment>
		<Segment><SegStyle>5</SegStyle><End><X>-15.050</X><Y>-22.452</Y></End></Segment>
		<Segment><SegStyle>3</SegStyle><End><X>-17.486</X><Y>-29.950</Y></End></Segment>
		<Segment><SegStyle>5</SegStyle><End><X>-17.560</X><Y>-29.950</Y></End></Segment>
		<Segment><SegStyle>3</SegStyle><End><X>-15.050</X><Y>-22.226</Y></End></Segment>
		<Segment><SegStyle>5</SegStyle><End><X>-15.050</X><Y>-21.999</Y></End></Segment>
		<Segment><SegStyle>3</SegStyle><End><X>-17.633</X><Y>-29.950</Y></End></Segment>
		<Segment><SegStyle>5</SegStyle><End><X>-17.707</X><Y>-29.950</Y></End></Segment>
		<Segment><SegStyle>3</SegStyle><End><X>-15.050</X><Y>-21.772</Y></End></Segment>
		<Segment><SegStyle>5</SegStyle><End><X>-15.050</X><Y>-21.546</Y></End></Segment>
		<Segment><SegStyle>3</SegStyle><End><X>-17.781</X><Y>-29.950</Y></End></Segment>
		<Segment><SegStyle>5</SegStyle><End><X>-17.854</X><Y>-29.950</Y></End></Segment>
		<Segment><SegStyle>3</SegStyle><End><X>-15.053</X><Y>-21.330</Y></End></Segment>
		<Segment><SegStyle>5</SegStyle><End><X>-15.109</X><Y>-21.274</Y></End></Segment>
		<Segment><SegStyle>3</SegStyle><End><X>-17.928</X><Y>-29.950</Y></End></Segment>
		<Segment><SegStyle>5</SegStyle><End><X>-18.001</X><Y>-29.950</Y></End></Segment>
		<Segment><SegStyle>3</SegStyle><End><X>-15.164</X><Y>-21.219</Y></End></Segment>
		<Segment><SegStyle>5</SegStyle><End><X>-15.220</X><Y>-21.163</Y></End></Segment>
		<Segment><SegStyle>3</SegStyle><End><X>-18.075</X><Y>-29.950</Y></End></Segment>
		<Segment><SegStyle>5</SegStyle><End><X>-18.149</X><Y>-29.950</Y></End></Segment>
		<Segment><SegStyle>3</SegStyle><End><X>-15.276</X><Y>-21.108</Y></End></Segment>
		<Segment><SegStyle>5</SegStyle><End><X>-15.331</X><Y>-21.052</Y></End></Segment>
		<Segment><SegStyle>3</SegStyle><End><X>-18.222</X><Y>-29.950</Y></End></Segment>
		<Segment><SegStyle>5</SegStyle><End><X>-18.296</X><Y>-29.950</Y></End></Segment>
		<Segment><SegStyle>3</SegStyle><End><X>-15.387</X><Y>-20.997</Y></End></Segment>
		<Segment><SegStyle>5</SegStyle><End><X>-15.442</X><Y>-20.941</Y></End></Segment>
		<Segment><SegStyle>3</SegStyle><End><X>-18.369</X><Y>-29.950</Y></End></Segment>
		<Segment><SegStyle>5</SegStyle><End><X>-18.443</X><Y>-29.950</Y></End></Segment>
		<Segment><SegStyle>3</SegStyle><End><X>-15.498</X><Y>-20.885</Y></End></Segment>
		<Segment><SegStyle>5</SegStyle><End><X>-15.553</X><Y>-20.830</Y></End></Segment>
		<Segment><SegStyle>3</SegStyle><End><X>-18.517</X><Y>-29.950</Y></End></Segment>
		<Segment><SegStyle>5</SegStyle><End><X>-18.590</X><Y>-29.950</Y></End></Segment>
		<Segment><SegStyle>3</SegStyle><End><X>-15.609</X><Y>-20.774</Y></End></Segment>
		<Segment><SegStyle>5</SegStyle><End><X>-15.664</X><Y>-20.719</Y></End></Segment>
		<Segment><SegStyle>3</SegStyle><End><X>-18.664</X><Y>-29.950</Y></End></Segment>
		<Segment><SegStyle>5</SegStyle><End><X>-18.737</X><Y>-29.950</Y></End></Segment>
		<Segment><SegStyle>3</SegStyle><End><X>-15.720</X><Y>-20.663</Y></End></Segment>
		<Segment><SegStyle>5</SegStyle><End><X>-15.776</X><Y>-20.608</Y></End></Segment>
		<Segment><SegStyle>3</SegStyle><End><X>-18.811</X><Y>-29.950</Y></End></Segment>
		<Segment><SegStyle>5</SegStyle><End><X>-18.885</X><Y>-29.950</Y></End></Segment>
		<Segment><SegStyle>3</SegStyle><End><X>-15.831</X><Y>-20.552</Y></End></Segment>
		<Segment><SegStyle>5</SegStyle><End><X>-15.887</X><Y>-20.497</Y></End></Segment>
		<Segment><SegStyle>3</SegStyle><End><X>-18.958</X><Y>-29.950</Y></End></Segment>
		<Segment><SegStyle>5</SegStyle><End><X>-19.032</X><Y>-29.950</Y></End></Segment>
		<Segment><SegStyle>3</SegStyle><End><X>-15.942</X><Y>-20.441</Y></End></Segment>
		<Segment><SegStyle>5</SegStyle><End><X>-15.998</X><Y>-20.385</Y></End></Segment>
		<Segment><SegStyle>3</SegStyle><End><X>-19.105</X><Y>-29.950</Y></End></Segment>
		<Segment><SegStyle>5</SegStyle><End><X>-19.179</X><Y>-29.950</Y></End></Segment>
		<Segment><SegStyle>3</SegStyle><End><X>-16.053</X><Y>-20.330</Y></End></Segment>
		<Segment><SegStyle>5</SegStyle><End><X>-16.109</X><Y>-20.274</Y></End></Segment>
		<Segment><SegStyle>3</SegStyle><End><X>-19.253</X><Y>-29.950</Y></End></Segment>
		<Segment><SegStyle>5</SegStyle><End><X>-19.326</X><Y>-29.950</Y></End></Segment>
		<Segment><SegStyle>3</SegStyle><End><X>-16.164</X><Y>-20.219</Y></End></Segment>
		<Segment><SegStyle>5</SegStyle><End><X>-16.220</X><Y>-20.163</Y></End></Segment>
		<Segment><SegStyle>3</SegStyle><End><X>-19.400</X><Y>-29.950</Y></End></Segment>
		<Segment><SegStyle>5</SegStyle><End><X>-19.473</X><Y>-29.950</Y></End></Segment>
		<Segment><SegStyle>3</SegStyle><End><X>-16.276</X><Y>-20.108</Y></End></Segment>
		<Segment><SegStyle>5</SegStyle><End><X>-16.331</X><Y>-20.052</Y></End></Segment>
		<Segment><SegStyle>3</SegStyle><End><X>-19.547</X><Y>-29.950</Y></End></Segment>
		<Segment><SegStyle>5</SegStyle><End><X>-19.621</X><Y>-29.950</Y></End></Segment>
		<Segment><SegStyle>3</SegStyle><End><X>-16.387</X><Y>-19.997</Y></End></Segment>
		<Segment><SegStyle>5</SegStyle><End><X>-16.442</X><Y>-19.941</Y></End></Segment>
		<Segment><SegStyle>3</SegStyle><End><X>-19.694</X><Y>-29.950</Y></End></Segment>
		<Segment><SegStyle>5</SegStyle><End><X>-19.768</X><Y>-29.950</Y></End></Segment>
		<Segment><SegStyle>3</SegStyle><End><X>-16.498</X><Y>-19.885</Y></End></Segment>
		<Segment><SegStyle>5</SegStyle><End><X>-16.553</X><Y>-19.830</Y></End></Segment>
		<Segment><SegStyle>3</SegStyle><End><X>-19.842</X><Y>-29.950</Y></End></Segment>
		<Segment><SegStyle>5</SegStyle><End><X>-19.915</X><Y>-29.950</Y></End></Segment>
		<Segment><SegStyle>3</SegStyle><End><X>-16.609</X><Y>-19.774</Y></End></Segment>
		<Segment><SegStyle>5</SegStyle><End><X>-16.664</X><Y>-19.719</Y></End></Segment>
		<Segment><SegStyle>3</SegStyle><End><X>-19.989</X><Y>-29.950</Y></End></Segment>
		<Segment><SegStyle>5</SegStyle><End><X>-20.062</X><Y>-29.950</Y></End></Segment>
		<Segment><SegStyle>3</SegStyle><End><X>-16.720</X><Y>-19.663</Y></End></Segment>
		<Segment><SegStyle>5</SegStyle><End><X>-16.776</X><Y>-19.608</Y></End></Segment>
		<Segment><SegStyle>3</SegStyle><End><X>-20.136</X><Y>-29.950</Y></End></Segment>
		<Segment><SegStyle>5</SegStyle><End><X>-20.210</X><Y>-29.950</Y></End></Segment>
		<Segment><SegStyle>3</SegStyle><End><X>-16.831</X><Y>-19.552</Y></End></Segment>
		<Segment><SegStyle>5</SegStyle><End><X>-16.887</X><Y>-19.497</Y></End></Segment>
		<Segment><SegStyle>3</SegStyle><End><X>-20.283</X><Y>-29.950</Y></End></Segment>
		<Segment><SegStyle>5</SegStyle><End><X>-20.357</X><Y>-29.950</Y></End></Segment>
		<Segment><SegStyle>3</SegStyle><End><X>-16.942</X><Y>-19.441</Y></End></Segment>
		<Segment><SegStyle>5</SegStyle><End><X>-16.998</X><Y>-19.386</Y></End></Segment>
		<Segment><SegStyle>3</SegStyle><End><X>-20.430</X><Y>-29.950</Y></End></Segment>
		<Segment><SegStyle>5</SegStyle><End><X>-20.504</X><Y>-29.950</Y></End></Segment>
		<Segment><SegStyle>3</SegStyle><End><X>-17.053</X><Y>-19.330</Y></End></Segment>
		<Segment><SegStyle>5</SegStyle><End><X>-17.109</X><Y>-19.274</Y></End></Segment>
		<Segment><SegStyle>3</SegStyle><End><X>-20.578</X><Y>-29.950</Y></End></Segment>
		<Segment><SegStyle>5</SegStyle><End><X>-20.651</X><Y>-29.950</Y></End></Segment>
		<Segment><SegStyle>3</SegStyle><End><X>-17.164</X><Y>-19.219</Y></End></Segment>
		<Segment><SegStyle>5</SegStyle><End><X>-17.220</X><Y>-19.163</Y></End></Segment>
		<Segment><SegStyle>3</SegStyle><End><X>-20.725</X><Y>-29.950</Y></End></Segment>
		<Segment><SegStyle>5</SegStyle><End><X>-20.798</X><Y>-29.950</Y></End></Segment>
		<Segment><SegStyle>3</SegStyle><End><X>-17.275</X><Y>-19.108</Y></End></Segment>
		<Segment><SegStyle>5</SegStyle><End><X>-17.331</X><Y>-19.052</Y></End></Segment>
		<Segment><SegStyle>3</SegStyle><End><X>-20.872</X><Y>-29.950</Y></End></Segment>
		<Segment><SegStyle>5</SegStyle><End><X>-20.946</X><Y>-29.950</Y></End></Segment>
		<Segment><SegStyle>3</SegStyle><End><X>-17.387</X><Y>-18.997</Y></End></Segment>
		<Segment><SegStyle>5</SegStyle><End><X>-17.442</X><Y>-18.941</Y></End></Segment>
		<Segment><SegStyle>3</SegStyle><End><X>-21.019</X><Y>-29.950</Y></End></Segment>
		<Segment><SegStyle>5</SegStyle><End><X>-21.093</X><Y>-29.950</Y></End></Segment>
		<Segment><SegStyle>3</SegStyle><End><X>-17.498</X><Y>-18.886</Y></End></Segment>
		<Segment><SegStyle>5</SegStyle><End><X>-17.553</X><Y>-18.830</Y></End></Segment>
		<Segment><SegStyle>3</SegStyle><End><X>-21.166</X><Y>-29.950</Y></End></Segment>
		<Segment><SegStyle>5</SegStyle><End><X>-21.240</X><Y>-29.950</Y></End></Segment>
		<Segment><SegStyle>3</SegStyle><End><X>-17.609</X><Y>-18.774</Y></End></Segment>
		<Segment><SegStyle>5</SegStyle><End><X>-17.664</X><Y>-18.719</Y></End></Segment>
		<Segment><SegStyle>3</SegStyle><End><X>-21.314</X><Y>-29.950</Y></End></Segment>
		<Segment><SegStyle>5</SegStyle><End><X>-21.387</X><Y>-29.950</Y></End></Segment>
		<Segment><SegStyle>3</SegStyle><End><X>-17.720</X><Y>-18.663</Y></End></Segment>
		<Segment><SegStyle>5</SegStyle><End><X>-17.775</X><Y>-18.608</Y></End></Segment>
		<Segment><SegStyle>3</SegStyle><End><X>-21.461</X><Y>-29.950</Y></End></Segment>
		<Segment><SegStyle>5</SegStyle><End><X>-21.534</X><Y>-29.950</Y></End></Segment>
		<Segment><SegStyle>3</SegStyle><End><X>-17.831</X><Y>-18.552</Y></End></Segment>
		<Segment><SegStyle>5</SegStyle><End><X>-17.887</X><Y>-18.497</Y></End></Segment>
		<Segment><SegStyle>3</SegStyle><End><X>-21.608</X><Y>-29.950</Y></End></Segment>
		<Segment><SegStyle>5</SegStyle><End><X>-21.682</X><Y>-29.950</Y></End></Segment>
		<Segment><SegStyle>3</SegStyle><End><X>-17.942</X><Y>-18.441</Y></End></Segment>
		<Segment><SegStyle>5</SegStyle><End><X>-17.998</X><Y>-18.386</Y></End></Segment>
		<Segment><SegStyle>3</SegStyle><End><X>-21.755</X><Y>-29.950</Y></End></Segment>
		<Segment><SegStyle>5</SegStyle><End><X>-21.829</X><Y>-29.950</Y></End></Segment>
		<Segment><SegStyle>3</SegStyle><End><X>-18.053</X><Y>-18.330</Y></End></Segment>
		<Segment><SegStyle>5</SegStyle><End><X>-18.109</X><Y>-18.274</Y></End></Segment>
		<Segment><SegStyle>3</SegStyle><End><X>-21.902</X><Y>-29.950</Y></End></Segment>
		<Segment><SegStyle>5</SegStyle><End><X>-21.976</X><Y>-29.950</Y></End></Segment>
		<Segment><SegStyle>3</SegStyle><End><X>-18.164</X><Y>-18.219</Y></End></Segment>
		<Segment><SegStyle>5</SegStyle><End><X>-18.220</X><Y>-18.163</Y></End></Segment>
		<Segment><SegStyle>3</SegStyle><End><X>-22.050</X><Y>-29.950</Y></End></Segment>
		<Segment><SegStyle>5</SegStyle><End><X>-22.123</X><Y>-29.950</Y></End></Segment>
		<Segment><SegStyle>3</SegStyle><End><X>-18.275</X><Y>-18.108</Y></End></Segment>
		<Segment><SegStyle>5</SegStyle><End><X>-18.331</X><Y>-18.052</Y></End></Segment>
		<Segment><SegStyle>3</SegStyle><End><X>-22.197</X><Y>-29.950</Y></End></Segment>
		<Segment><SegStyle>5</SegStyle><End><X>-22.270</X><Y>-29.950</Y></End></Segment>
		<Segment><SegStyle>3</SegStyle><End><X>-18.387</X><Y>-17.997</Y></End></Segment>
		<Segment><SegStyle>5</SegStyle><End><X>-18.442</X><Y>-17.941</Y></End></Segment>
		<Segment><SegStyle>3</SegStyle><End><X>-22.344</X><Y>-29.950</Y></End></Segment>
		<Segment><SegStyle>5</SegStyle><End><X>-22.418</X><Y>-29.950</Y></End></Segment>
		<Segment><SegStyle>3</SegStyle><End><X>-18.498</X><Y>-17.886</Y></End></Segment>
		<Segment><SegStyle>5</SegStyle><End><X>-18.553</X><Y>-17.830</Y></End></Segment>
		<Segment><SegStyle>3</SegStyle><End><X>-22.491</X><Y>-29.950</Y></End></Segment>
		<Segment><SegStyle>5</SegStyle><End><X>-22.565</X><Y>-29.950</Y></End></Segment>
		<Segment><SegStyle>3</SegStyle><End><X>-18.609</X><Y>-17.774</Y></End></Segment>
		<Segment><SegStyle>5</SegStyle><End><X>-18.664</X><Y>-17.719</Y></End></Segment>
		<Segment><SegStyle>3</SegStyle><End><X>-22.638</X><Y>-29.950</Y></End></Segment>
		<Segment><SegStyle>5</SegStyle><End><X>-22.712</X><Y>-29.950</Y></End></Segment>
		<Segment><SegStyle>3</SegStyle><End><X>-18.720</X><Y>-17.663</Y></End></Segment>
		<Segment><SegStyle>5</SegStyle><End><X>-18.775</X><Y>-17.608</Y></End></Segment>
		<Segment><SegStyle>3</SegStyle><End><X>-22.786</X><Y>-29.950</Y></End></Segment>
		<Segment><SegStyle>5</SegStyle><End><X>-22.859</X><Y>-29.950</Y></End></Segment>
		<Segment><SegStyle>3</SegStyle><End><X>-18.831</X><Y>-17.552</Y></End></Segment>
		<Segment><SegStyle>5</SegStyle><End><X>-18.886</X><Y>-17.497</Y></End></Segment>
		<Segment><SegStyle>3</SegStyle><End><X>-22.933</X><Y>-29.950</Y></End></Segment>
		<Segment><SegStyle>5</SegStyle><End><X>-23.006</X><Y>-29.950</Y></End></Segment>
		<Segment><SegStyle>3</SegStyle><End><X>-18.942</X><Y>-17.441</Y></End></Segment>
		<Segment><SegStyle>5</SegStyle><End><X>-18.998</X><Y>-17.386</Y></End></Segment>
		<Segment><SegStyle>3</SegStyle><End><X>-23.080</X><Y>-29.950</Y></End></Segment>
		<Segment><SegStyle>5</SegStyle><End><X>-23.154</X><Y>-29.950</Y></End></Segment>
		<Segment><SegStyle>3</SegStyle><End><X>-19.053</X><Y>-17.330</Y></End></Segment>
		<Segment><SegStyle>5</SegStyle><End><X>-19.109</X><Y>-17.275</Y></End></Segment>
		<Segment><SegStyle>3</SegStyle><End><X>-23.227</X><Y>-29.950</Y></End></Segment>
		<Segment><SegStyle>5</SegStyle><End><X>-23.301</X><Y>-29.950</Y></End></Segment>
		<Segment><SegStyle>3</SegStyle><End><X>-19.164</X><Y>-17.219</Y></End></Segment>
		<Segment><SegStyle>5</SegStyle><End><X>-19.220</X><Y>-17.163</Y></End></Segment>
		<Segment><SegStyle>3</SegStyle><End><X>-23.374</X><Y>-29.950</Y></End></Segment>
		<Segment><SegStyle>5</SegStyle><End><X>-23.448</X><Y>-29.950</Y></End></Segment>
		<Segment><SegStyle>3</SegStyle><End><X>-19.275</X><Y>-17.108</Y></End></Segment>
		<Segment><SegStyle>5</SegStyle><End><X>-19.331</X><Y>-17.052</Y></End></Segment>
		<Segment><SegStyle>3</SegStyle><End><X>-23.522</X><Y>-29.950</Y></End></Segment>
		<Segment><SegStyle>5</SegStyle><End><X>-23.595</X><Y>-29.950</Y></End></Segment>
		<Segment><SegStyle>3</SegStyle><End><X>-19.386</X><Y>-16.997</Y></End></Segment>
		<Segment><SegStyle>5</SegStyle><End><X>-19.442</X><Y>-16.941</Y></End></Segment>
		<Segment><SegStyle>3</SegStyle><End><X>-23.669</X><Y>-29.950</Y></End></Segment>
		<Segment><SegStyle>5</SegStyle><End><X>-23.742</X><Y>-29.950</Y></End></Segment>
		<Segment><SegStyle>3</SegStyle><End><X>-19.498</X><Y>-16.886</Y></End></Segment>
		<Segment><SegStyle>5</SegStyle><End><X>-19.553</X><Y>-16.830</Y></End></Segment>
		<Segment><SegStyle>3</SegStyle><End><X>-23.816</X><Y>-29.950</Y></End></Segment>
		<Segment><SegStyle>5</SegStyle><End><X>-23.890</X><Y>-29.950</Y></End></Segment>
		<Segment><SegStyle>3</SegStyle><End><X>-19.609</X><Y>-16.775</Y></End></Segment>
		<Segment><SegStyle>5</SegStyle><End><X>-19.664</X><Y>-16.719</Y></End></Segment>
		<Segment><SegStyle>3</SegStyle><End><X>-23.963</X><Y>-29.950</Y></End></Segment>
		<Segment><SegStyle>5</SegStyle><End><X>-24.037</X><Y>-29.950</Y></End></Segment>
		<Segment><SegStyle>3</SegStyle><End><X>-19.720</X><Y>-16.663</Y></End></Segment>
		<Segment><SegStyle>5</SegStyle><End><X>-19.775</X><Y>-16.608</Y></End></Segment>
		<Segment><SegStyle>3</SegStyle><End><X>-24.110</X><Y>-29.950</Y></End></Segment>
		<Segment><SegStyle>5</SegStyle><End><X>-24.184</X><Y>-29.950</Y></End></Segment>
		<Segment><SegStyle>3</SegStyle><End><X>-19.831</X><Y>-16.552</Y></End></Segment>
		<Segment><SegStyle>5</SegStyle><End><X>-19.886</X><Y>-16.497</Y></End></Segment>
		<Segment><SegStyle>3</SegStyle><End><X>-24.258</X><Y>-29.950</Y></End></Segment>
		<Segment><SegStyle>5</SegStyle><End><X>-24.331</X><Y>-29.950</Y></End></Segment>
		<Segment><SegStyle>3</SegStyle><End><X>-19.942</X><Y>-16.441</Y></End></Segment>
		<Segment><SegStyle>5</SegStyle><End><X>-19.998</X><Y>-16.386</Y></End></Segment>
		<Segment><SegStyle>3</SegStyle><End><X>-24.405</X><Y>-29.950</Y></End></Segment>
		<Segment><SegStyle>5</SegStyle><End><X>-24.478</X><Y>-29.950</Y></End></Segment>
		<Segment><SegStyle>3</SegStyle><End><X>-20.053</X><Y>-16.330</Y></End></Segment>
		<Segment><SegStyle>5</SegStyle><End><X>-20.109</X><Y>-16.275</Y></End></Segment>
		<Segment><SegStyle>3</SegStyle><End><X>-24.552</X><Y>-29.950</Y></End></Segment>
		<Segment><SegStyle>5</SegStyle><End><X>-24.626</X><Y>-29.950</Y></End></Segment>
		<Segment><SegStyle>3</SegStyle><End><X>-20.164</X><Y>-16.219</Y></End></Segment>
		<Segment><SegStyle>5</SegStyle><End><X>-20.220</X><Y>-16.163</Y></End></Segment>
		<Segment><SegStyle>3</SegStyle><End><X>-24.699</X><Y>-29.950</Y></End></Segment>
		<Segment><SegStyle>5</SegStyle><End><X>-24.773</X><Y>-29.950</Y></End></Segment>
		<Segment><SegStyle>3</SegStyle><End><X>-20.275</X><Y>-16.108</Y></End></Segment>
		<Segment><SegStyle>5</SegStyle><End><X>-20.331</X><Y>-16.052</Y></End></Segment>
		<Segment><SegStyle>3</SegStyle><End><X>-24.846</X><Y>-29.950</Y></End></Segment>
		<Segment><SegStyle>5</SegStyle><End><X>-24.920</X><Y>-29.950</Y></End></Segment>
		<Segment><SegStyle>3</SegStyle><End><X>-20.386</X><Y>-15.997</Y></End></Segment>
		<Segment><SegStyle>5</SegStyle><End><X>-20.442</X><Y>-15.941</Y></End></Segment>
		<Segment><SegStyle>3</SegStyle><End><X>-24.994</X><Y>-29.950</Y></End></Segment>
		<Segment><SegStyle>5</SegStyle><End><X>-25.067</X><Y>-29.950</Y></End></Segment>
		<Segment><SegStyle>3</SegStyle><End><X>-20.498</X><Y>-15.886</Y></End></Segment>
		<Segment><SegStyle>5</SegStyle><End><X>-20.553</X><Y>-15.830</Y></End></Segment>
		<Segment><SegStyle>3</SegStyle><End><X>-25.141</X><Y>-29.950</Y></End></Segment>
		<Segment><SegStyle>5</SegStyle><End><X>-25.214</X><Y>-29.950</Y></End></Segment>
		<Segment><SegStyle>3</SegStyle><End><X>-20.609</X><Y>-15.775</Y></End></Segment>
		<Segment><SegStyle>5</SegStyle><End><X>-20.664</X><Y>-15.719</Y></End></Segment>
		<Segment><SegStyle>3</SegStyle><End><X>-25.288</X><Y>-29.950</Y></End></Segment>
		<Segment><SegStyle>5</SegStyle><End><X>-25.362</X><Y>-29.950</Y></End></Segment>
		<Segment><SegStyle>3</SegStyle><End><X>-20.720</X><Y>-15.663</Y></End></Segment>
		<Segment><SegStyle>5</SegStyle><End><X>-20.775</X><Y>-15.608</Y></End></Segment>
		<Segment><SegStyle>3</SegStyle><End><X>-25.435</X><Y>-29.950</Y></End></Segment>
		<Segment><SegStyle>5</SegStyle><End><X>-25.509</X><Y>-29.950</Y></End></Segment>
		<Segment><SegStyle>3</SegStyle><End><X>-20.831</X><Y>-15.552</Y></End></Segment>
		<Segment><SegStyle>5</SegStyle><End><X>-20.886</X><Y>-15.497</Y></End></Segment>
		<Segment><SegStyle>3</SegStyle><End><X>-25.582</X><Y>-29.950</Y></End></Segment>
		<Segment><SegStyle>5</SegStyle><End><X>-25.656</X><Y>-29.950</Y></End></Segment>
		<Segment><SegStyle>3</SegStyle><End><X>-20.942</X><Y>-15.441</Y></End></Segment>
		<Segment><SegStyle>5</SegStyle><End><X>-20.997</X><Y>-15.386</Y></End></Segment>
		<Segment><SegStyle>3</SegStyle><End><X>-25.730</X><Y>-29.950</Y></End></Segment>
		<Segment><SegStyle>5</SegStyle><End><X>-25.803</X><Y>-29.950</Y></End></Segment>
		<Segment><SegStyle>3</SegStyle><End><X>-21.053</X><Y>-15.330</Y></End></Segment>
		<Segment><SegStyle>5</SegStyle><End><X>-21.109</X><Y>-15.275</Y></End></Segment>
		<Segment><SegStyle>3</SegStyle><End><X>-25.877</X><Y>-29.950</Y></End></Segment>
		<Segment><SegStyle>5</SegStyle><End><X>-25.951</X><Y>-29.950</Y></End></Segment>
		<Segment><SegStyle>3</SegStyle><End><X>-21.164</X><Y>-15.219</Y></End></Segment>
		<Segment><SegStyle>5</SegStyle><End><X>-21.220</X><Y>-15.164</Y></End></Segment>
		<Segment><SegStyle>3</SegStyle><End><X>-26.024</X><Y>-29.950</Y></End></Segment>
		<Segment><SegStyle>5</SegStyle><End><X>-26.098</X><Y>-29.950</Y></End></Segment>
		<Segment><SegStyle>3</SegStyle><End><X>-21.275</X><Y>-15.108</Y></End></Segment>
		<Segment><SegStyle>5</SegStyle><End><X>-21.331</X><Y>-15.052</Y></End></Segment>
		<Segment><SegStyle>3</SegStyle><End><X>-26.171</X><Y>-29.950</Y></End></Segment>
		<Segment><SegStyle>5</SegStyle><End><X>-26.245</X><Y>-29.950</Y></End></Segment>
		<Segment><SegStyle>3</SegStyle><End><X>-21.404</X><Y>-15.050</Y></End></Segment>
		<Segment><SegStyle>5</SegStyle><End><X>-21.477</X><Y>-15.050</Y></End></Segment>
		<Segment><SegStyle>3</SegStyle><End><X>-26.319</X><Y>-29.950</Y></End></Segment>
		<Segment><SegStyle>5</SegStyle><End><X>-26.392</X><Y>-29.950</Y></End></Segment>
		<Segment><SegStyle>3</SegStyle><End><X>-21.551</X><Y>-15.050</Y></End></Segment>
		<Segment><SegStyle>5</SegStyle><End><X>-21.624</X><Y>-15.050</Y></End></Segment>
		<Segment><SegStyle>3</SegStyle><End><X>-26.466</X><Y>-29.950</Y></End></Segment>
		<Segment><SegStyle>5</SegStyle><End><X>-26.539</X><Y>-29.950</Y></End></Segment>
		<Segment><SegStyle>3</SegStyle><End><X>-21.698</X><Y>-15.050</Y></End></Segment>
		<Segment><SegStyle>5</SegStyle><End><X>-21.772</X><Y>-15.050</Y></End></Segment>
		<Segment><SegStyle>3</SegStyle><End><X>-26.613</X><Y>-29.950</Y></End></Segment>
		<Segment><SegStyle>5</SegStyle><End><X>-26.687</X><Y>-29.950</Y></End></Segment>
		<Segment><SegStyle>3</SegStyle><End><X>-21.845</X><Y>-15.050</Y></End></Segment>
		<Segment><SegStyle>5</SegStyle><End><X>-21.919</X><Y>-15.050</Y></End></Segment>
		<Segment><SegStyle>3</SegStyle><End><X>-26.760</X><Y>-29.950</Y></End></Segment>
		<Segment><SegStyle>5</SegStyle><End><X>-26.834</X><Y>-29.950</Y></End></Segment>
		<Segment><SegStyle>3</SegStyle><End><X>-21.992</X><Y>-15.050</Y></End></Segment>
		<Segment><SegStyle>5</SegStyle><End><X>-22.066</X><Y>-15.050</Y></End></Segment>
		<Segment><SegStyle>3</SegStyle><End><X>-26.907</X><Y>-29.950</Y></End></Segment>
		<Segment><SegStyle>5</SegStyle><End><X>-26.981</X><Y>-29.950</Y></End></Segment>
		<Segment><SegStyle>3</SegStyle><End><X>-22.140</X><Y>-15.050</Y></End></Segment>
		<Segment><SegStyle>5</SegStyle><End><X>-22.213</X><Y>-15.050</Y></End></Segment>
		<Segment><SegStyle>3</SegStyle><End><X>-27.055</X><Y>-29.950</Y></End></Segment>
		<Segment><SegStyle>5</SegStyle><End><X>-27.128</X><Y>-29.950</Y></End></Segment>
		<Segment><SegStyle>3</SegStyle><End><X>-22.287</X><Y>-15.050</Y></End></Segment>
		<Segment><SegStyle>5</SegStyle><End><X>-22.360</X><Y>-15.050</Y></End></Segment>
		<Segment><SegStyle>3</SegStyle><End><X>-27.202</X><Y>-29.950</Y></End></Segment>
		<Segment><SegStyle>5</SegStyle><End><X>-27.275</X><Y>-29.950</Y></End></Segment>
		<Segment><SegStyle>3</SegStyle><End><X>-22.434</X><Y>-15.050</Y></End></Segment>
		<Segment><SegStyle>5</SegStyle><End><X>-22.508</X><Y>-15.050</Y></End></Segment>
		<Segment><SegStyle>3</SegStyle><End><X>-27.349</X><Y>-29.950</Y></End></Segment>
		<Segment><SegStyle>5</SegStyle><End><X>-27.423</X><Y>-29.950</Y></End></Segment>
		<Segment><SegStyle>3</SegStyle><End><X>-22.581</X><Y>-15.050</Y></End></Segment>
		<Segment><SegStyle>5</SegStyle><End><X>-22.655</X><Y>-15.050</Y></End></Segment>
		<Segment><SegStyle>3</SegStyle><End><X>-27.496</X><Y>-29.950</Y></End></Segment>
		<Segment><SegStyle>5</SegStyle><End><X>-27.570</X><Y>-29.950</Y></End></Segment>
		<Segment><SegStyle>3</SegStyle><End><X>-22.728</X><Y>-15.050</Y></End></Segment>
		<Segment><SegStyle>5</SegStyle><End><X>-22.802</X><Y>-15.050</Y></End></Segment>
		<Segment><SegStyle>3</SegStyle><End><X>-27.643</X><Y>-29.950</Y></End></Segment>
		<Segment><SegStyle>5</SegStyle><End><X>-27.717</X><Y>-29.950</Y></End></Segment>
		<Segment><SegStyle>3</SegStyle><End><X>-22.876</X><Y>-15.050</Y></End></Segment>
		<Segment><SegStyle>5</SegStyle><End><X>-22.949</X><Y>-15.050</Y></End></Segment>
		<Segment><SegStyle>3</SegStyle><End><X>-27.791</X><Y>-29.950</Y></End></Segment>
		<Segment><SegStyle>5</SegStyle><End><X>-27.864</X><Y>-29.950</Y></End></Segment>
		<Segment><SegStyle>3</SegStyle><End><X>-23.023</X><Y>-15.050</Y></End></Segment>
		<Segment><SegStyle>5</SegStyle><End><X>-23.096</X><Y>-15.050</Y></End></Segment>
		<Segment><SegStyle>3</SegStyle><End><X>-27.938</X><Y>-29.950</Y></End></Segment>
		<Segment><SegStyle>5</SegStyle><End><X>-28.011</X><Y>-29.950</Y></End></Segment>
		<Segment><SegStyle>3</SegStyle><End><X>-23.170</X><Y>-15.050</Y></End></Segment>
		<Segment><SegStyle>5</SegStyle><End><X>-23.244</X><Y>-15.050</Y></End></Segment>
		<Segment><SegStyle>3</SegStyle><End><X>-28.085</X><Y>-29.950</Y></End></Segment>
		<Segment><SegStyle>5</SegStyle><End><X>-28.159</X><Y>-29.950</Y></End></Segment>
		<Segment><SegStyle>3</SegStyle><End><X>-23.317</X><Y>-15.050</Y></End></Segment>
		<Segment><SegStyle>5</SegStyle><End><X>-23.391</X><Y>-15.050</Y></End></Segment>
		<Segment><SegStyle>3</SegStyle><End><X>-28.232</X><Y>-29.950</Y></End></Segment>
		<Segment><SegStyle>5</SegStyle><End><X>-28.306</X><Y>-29.950</Y></End></Segment>
		<Segment><SegStyle>3</SegStyle><End><X>-23.464</X><Y>-15.050</Y></End></Segment>
		<Segment><SegStyle>5</SegStyle><End><X>-23.538</X><Y>-15.050</Y></End></Segment>
		<Segment><SegStyle>3</SegStyle><End><X>-28.379</X><Y>-29.950</Y></End></Segment>
		<Segment><SegStyle>5</SegStyle><End><X>-28.453</X><Y>-29.950</Y></End></Segment>
		<Segment><SegStyle>3</SegStyle><End><X>-23.612</X><Y>-15.050</Y></End></Segment>
		<Segment><SegStyle>5</SegStyle><End><X>-23.685</X><Y>-15.050</Y></End></Segment>
		<Segment><SegStyle>3</SegStyle><End><X>-28.527</X><Y>-29.950</Y></End></Segment>
		<Segment><SegStyle>5</SegStyle><End><X>-28.600</X><Y>-29.950</Y></End></Segment>
		<Segment><SegStyle>3</SegStyle><End><X>-23.759</X><Y>-15.050</Y></End></Segment>
		<Segment><SegStyle>5</SegStyle><End><X>-23.832</X><Y>-15.050</Y></End></Segment>
		<Segment><SegStyle>3</SegStyle><End><X>-28.674</X><Y>-29.950</Y></End></Segment>
		<Segment><SegStyle>5</SegStyle><End><X>-28.747</X><Y>-29.950</Y></End></Segment>
		<Segment><SegStyle>3</SegStyle><End><X>-23.906</X><Y>-15.050</Y></End></Segment>
		<Segment><SegStyle>5</SegStyle><End><X>-23.980</X><Y>-15.050</Y></End></Segment>
		<Segment><SegStyle>3</SegStyle><End><X>-28.821</X><Y>-29.950</Y></End></Segment>
		<Segment><SegStyle>5</SegStyle><End><X>-28.895</X><Y>-29.950</Y></End></Segment>
		<Segment><SegStyle>3</SegStyle><End><X>-24.053</X><Y>-15.050</Y></End></Segment>
		<Segment><SegStyle>5</SegStyle><End><X>-24.127</X><Y>-15.050</Y></End></Segment>
		<Segment><SegStyle>3</SegStyle><End><X>-28.968</X><Y>-29.950</Y></End></Segment>
		<Segment><SegStyle>5</SegStyle><End><X>-29.042</X><Y>-29.950</Y></End></Segment>
		<Segment><SegStyle>3</SegStyle><End><X>-24.201</X><Y>-15.050</Y></End></Segment>
		<Segment><SegStyle>5</SegStyle><End><X>-24.274</X><Y>-15.050</Y></End></Segment>
		<Segment><SegStyle>3</SegStyle><End><X>-29.115</X><Y>-29.950</Y></End></Segment>
		<Segment><SegStyle>5</SegStyle><End><X>-29.189</X><Y>-29.950</Y></End></Segment>
		<Segment><SegStyle>3</SegStyle><End><X>-24.348</X><Y>-15.050</Y></End></Segment>
		<Segment><SegStyle>5</SegStyle><End><X>-24.421</X><Y>-15.050</Y></End></Segment>
		<Segment><SegStyle>3</SegStyle><End><X>-29.263</X><Y>-29.950</Y></End></Segment>
		<Segment><SegStyle>5</SegStyle><End><X>-29.336</X><Y>-29.950</Y></End></Segment>
		<Segment><SegStyle>3</SegStyle><End><X>-24.495</X><Y>-15.050</Y></End></Segment>
		<Segment><SegStyle>5</SegStyle><End><X>-24.569</X><Y>-15.050</Y></End></Segment>
		<Segment><SegStyle>3</SegStyle><End><X>-29.410</X><Y>-29.950</Y></End></Segment>
		<Segment><SegStyle>5</SegStyle><End><X>-29.483</X><Y>-29.950</Y></End></Segment>
		<Segment><SegStyle>3</SegStyle><End><X>-24.642</X><Y>-15.050</Y></End></Segment>
		<Segment><SegStyle>5</SegStyle><End><X>-24.716</X><Y>-15.050</Y></End></Segment>
		<Segment><SegStyle>3</SegStyle><End><X>-29.557</X><Y>-29.950</Y></End></Segment>
		<Segment><SegStyle>5</SegStyle><End><X>-29.631</X><Y>-29.950</Y></End></Segment>
		<Segment><SegStyle>3</SegStyle><End><X>-24.789</X><Y>-15.050</Y></End></Segment>
		<Segment><SegStyle>5</SegStyle><End><X>-24.863</X><Y>-15.050</Y></End></Segment>
		<Segment><SegStyle>3</SegStyle><End><X>-29.704</X><Y>-29.950</Y></End></Segment>
		<Segment><SegStyle>5</SegStyle><End><X>-29.778</X><Y>-29.950</Y></End></Segment>
		<Segment><SegStyle>3</SegStyle><End><X>-24.937</X><Y>-15.050</Y></End></Segment>
		<Segment><SegStyle>5</SegStyle><End><X>-25.010</X><Y>-15.050</Y></End></Segment>
		<Segment><SegStyle>3</SegStyle><End><X>-29.851</X><Y>-29.950</Y></End></Segment>
		<Segment><SegStyle>5</SegStyle><End><X>-29.925</X><Y>-29.950</Y></End></Segment>
		<Segment><SegStyle>3</SegStyle><End><X>-25.084</X><Y>-15.050</Y></End></Segment>
		<Segment><SegStyle>5</SegStyle><End><X>-25.157</X><Y>-15.050</Y></End></Segment>
		<Segment><SegStyle>3</SegStyle><End><X>-29.950</X><Y>-29.800</Y></End></Segment>
		<Segment><SegStyle>5</SegStyle><End><X>-29.950</X><Y>-29.574</Y></End></Segment>
		<Segment><SegStyle>3</SegStyle><End><X>-25.231</X><Y>-15.050</Y></End></Segment>
		<Segment><SegStyle>5</SegStyle><End><X>-25.305</X><Y>-15.050</Y></End></Segment>
		<Segment><SegStyle>3</SegStyle><End><X>-29.950</X><Y>-29.347</Y></End></Segment>
		<Segment><SegStyle>5</SegStyle><End><X>-29.950</X><Y>-29.121</Y></End></Segment>
		<Segment><SegStyle>3</SegStyle><End><X>-25.378</X><Y>-15.050</Y></End></Segment>
		<Segment><SegStyle>5</SegStyle><End><X>-25.452</X><Y>-15.050</Y></End></Segment>
		<Segment><SegStyle>3</SegStyle><End><X>-29.950</X><Y>-28.894</Y></End></Segment>
		<Segment><SegStyle>5</SegStyle><End><X>-29.950</X><Y>-28.668</Y></End></Segment>
		<Segment><SegStyle>3</SegStyle><End><X>-25.525</X><Y>-15.050</Y></End></Segment>
		<Segment><SegStyle>5</SegStyle><End><X>-25.599</X><Y>-15.050</Y></End></Segment>
		<Segment><SegStyle>3</SegStyle><End><X>-29.950</X><Y>-28.441</Y></End></Segment>
		<Segment><SegStyle>5</SegStyle><End><X>-29.950</X><Y>-28.215</Y></End></Segment>
		<Segment><SegStyle>3</SegStyle><End><X>-25.673</X><Y>-15.050</Y></End></Segment>
		<Segment><SegStyle>5</SegStyle><End><X>-25.746</X><Y>-15.050</Y></End></Segment>
		<Segment><SegStyle>3</SegStyle><End><X>-29.950</X><Y>-27.988</Y></End></Segment>
		<Segment><SegStyle>5</SegStyle><End><X>-29.950</X><Y>-27.762</Y></End></Segment>
		<Segment><SegStyle>3</SegStyle><End><X>-25.820</X><Y>-15.050</Y></End></Segment>
		<Segment><SegStyle>5</SegStyle><End><X>-25.893</X><Y>-15.050</Y></End></Segment>
		<Segment><SegStyle>3</SegStyle><End><X>-29.950</X><Y>-27.535</Y></End></Segment>
		<Segment><SegStyle>5</SegStyle><End><X>-29.950</X><Y>-27.309</Y></End></Segment>
		<Segment><SegStyle>3</SegStyle><End><X>-25.967</X><Y>-15.050</Y></End></Segment>
		<Segment><SegStyle>5</SegStyle><End><X>-26.041</X><Y>-15.050</Y></End></Segment>
		<Segment><SegStyle>3</SegStyle><End><X>-29.950</X><Y>-27.082</Y></End></Segment>
		<Segment><SegStyle>5</SegStyle><End><X>-29.950</X><Y>-26.855</Y></End></Segment>
		<Segment><SegStyle>3</SegStyle><End><X>-26.114</X><Y>-15.050</Y></End></Segment>
		<Segment><SegStyle>5</SegStyle><End><X>-26.188</X><Y>-15.050</Y></End></Segment>
		<Segment><SegStyle>3</SegStyle><End><X>-29.950</X><Y>-26.629</Y></End></Segment>
		<Segment><SegStyle>5</SegStyle><End><X>-29.950</X><Y>-26.402</Y></End></Segment>
		<Segment><SegStyle>3</SegStyle><End><X>-26.261</X><Y>-15.050</Y></End></Segment>
		<Segment><SegStyle>5</SegStyle><End><X>-26.335</X><Y>-15.050</Y></End></Segment>
		<Segment><SegStyle>3</SegStyle><End><X>-29.950</X><Y>-26.176</Y></End></Segment>
		<Segment><SegStyle>5</SegStyle><End><X>-29.950</X><Y>-25.949</Y></End></Segment>
		<Segment><SegStyle>3</SegStyle><End><X>-26.409</X><Y>-15.050</Y></End></Segment>
		<Segment><SegStyle>5</SegStyle><End><X>-26.482</X><Y>-15.050</Y></End></Segment>
		<Segment><SegStyle>3</SegStyle><End><X>-29.950</X><Y>-25.723</Y></End></Segment>
		<Segment><SegStyle>5</SegStyle><End><X>-29.950</X><Y>-25.496</Y></End></Segment>
		<Segment><SegStyle>3</SegStyle><End><X>-26.556</X><Y>-15.050</Y></End></Segment>
		<Segment><SegStyle>5</SegStyle><End><X>-26.629</X><Y>-15.050</Y></End></Segment>
		<Segment><SegStyle>3</SegStyle><End><X>-29.950</X><Y>-25.270</Y></End></Segment>
		<Segment><SegStyle>5</SegStyle><End><X>-29.950</X><Y>-25.043</Y></End></Segment>
		<Segment><SegStyle>3</SegStyle><End><X>-26.703</X><Y>-15.050</Y></End></Segment>
		<Segment><SegStyle>5</SegStyle><End><X>-26.777</X><Y>-15.050</Y></End></Segment>
		<Segment><SegStyle>3</SegStyle><End><X>-29.950</X><Y>-24.817</Y></End></Segment>
		<Segment><SegStyle>5</SegStyle><End><X>-29.950</X><Y>-24.590</Y></End></Segment>
		<Segment><SegStyle>3</SegStyle><End><X>-26.850</X><Y>-15.050</Y></End></Segment>
		<Segment><SegStyle>5</SegStyle><End><X>-26.924</X><Y>-15.050</Y></End></Segment>
		<Segment><SegStyle>3</SegStyle><End><X>-29.950</X><Y>-24.364</Y></End></Segment>
		<Segment><SegStyle>5</SegStyle><End><X>-29.950</X><Y>-24.137</Y></End></Segment>
		<Segment><SegStyle>3</SegStyle><End><X>-26.997</X><Y>-15.050</Y></End></Segment>
		<Segment><SegStyle>5</SegStyle><End><X>-27.071</X><Y>-15.050</Y></End></Segment>
		<Segment><SegStyle>3</SegStyle><End><X>-29.950</X><Y>-23.911</Y></End></Segment>
		<Segment><SegStyle>5</SegStyle><End><X>-29.950</X><Y>-23.684</Y></End></Segment>
		<Segment><SegStyle>3</SegStyle><End><X>-27.145</X><Y>-15.050</Y></End></Segment>
		<Segment><SegStyle>5</SegStyle><End><X>-27.218</X><Y>-15.050</Y></End></Segment>
		<Segment><SegStyle>3</SegStyle><End><X>-29.950</X><Y>-23.458</Y></End></Segment>
		<Segment><SegStyle>5</SegStyle><End><X>-29.950</X><Y>-23.231</Y></End></Segment>
		<Segment><SegStyle>3</SegStyle><End><X>-27.292</X><Y>-15.050</Y></End></Segment>
		<Segment><SegStyle>5</SegStyle><End><X>-27.365</X><Y>-15.050</Y></End></Segment>
		<Segment><SegStyle>3</SegStyle><End><X>-29.950</X><Y>-23.005</Y></End></Segment>
		<Segment><SegStyle>5</SegStyle><End><X>-29.950</X><Y>-22.778</Y></End></Segment>
		<Segment><SegStyle>3</SegStyle><End><X>-27.439</X><Y>-15.050</Y></End></Segment>
		<Segment><SegStyle>5</SegStyle><End><X>-27.513</X><Y>-15.050</Y></End></Segment>
		<Segment><SegStyle>3</SegStyle><End><X>-29.950</X><Y>-22.552</Y></End></Segment>
		<Segment><SegStyle>5</SegStyle><End><X>-29.950</X><Y>-22.325</Y></End></Segment>
		<Segment><SegStyle>3</SegStyle><End><X>-27.586</X><Y>-15.050</Y></End></Segment>
		<Segment><SegStyle>5</SegStyle><End><X>-27.660</X><Y>-15.050</Y></End></Segment>
		<Segment><SegStyle>3</SegStyle><End><X>-29.950</X><Y>-22.098</Y></End></Segment>
		<Segment><SegStyle>5</SegStyle><End><X>-29.950</X><Y>-21.872</Y></End></Segment>
		<Segment><SegStyle>3</SegStyle><End><X>-27.733</X><Y>-15.050</Y></End></Segment>
		<Segment><SegStyle>5</SegStyle><End><X>-27.807</X><Y>-15.050</Y></End></Segment>
		<Segment><SegStyle>3</SegStyle><End><X>-29.950</X><Y>-21.645</Y></End></Segment>
		<Segment><SegStyle>5</SegStyle><End><X>-29.950</X><Y>-21.419</Y></End></Segment>
		<Segment><SegStyle>3</SegStyle><End><X>-27.881</X><Y>-15.050</Y></End></Segment>
		<Segment><SegStyle>5</SegStyle><End><X>-27.954</X><Y>-15.050</Y></End></Segment>
		<Segment><SegStyle>3</SegStyle><End><X>-29.950</X><Y>-21.192</Y></End></Segment>
		<Segment><SegStyle>5</SegStyle><End><X>-29.950</X><Y>-20.966</Y></End></Segment>
		<Segment><SegStyle>3</SegStyle><End><X>-28.028</X><Y>-15.050</Y></End></Segment>
		<Segment><SegStyle>5</SegStyle><End><X>-28.101</X><Y>-15.050</Y></End></Segment>
		<Segment><SegStyle>3</SegStyle><End><X>-29.950</X><Y>-20.739</Y></End></Segment>
		<Segment><SegStyle>5</SegStyle><End><X>-29.950</X><Y>-20.513</Y></End></Segment>
		<Segment><SegStyle>3</SegStyle><End><X>-28.175</X><Y>-15.050</Y></End></Segment>
		<Segment><SegStyle>5</SegStyle><End><X>-28.249</X><Y>-15.050</Y></End></Segment>
		<Segment><SegStyle>3</SegStyle><End><X>-29.950</X><Y>-20.286</Y></End></Segment>
		<Segment><SegStyle>5</SegStyle><End><X>-29.950</X><Y>-20.060</Y></End></Segment>
		<Segment><SegStyle>3</SegStyle><End><X>-28.322</X><Y>-15.050</Y></End></Segment>
		<Segment><SegStyle>5</SegStyle><End><X>-28.396</X><Y>-15.050</Y></End></Segment>
		<Segment><SegStyle>3</SegStyle><End><X>-29.950</X><Y>-19.833</Y></End></Segment>
		<Segment><SegStyle>5</SegStyle><End><X>-29.950</X><Y>-19.607</Y></End></Segment>
		<Segment><SegStyle>3</SegStyle><End><X>-28.469</X><Y>-15.050</Y></End></Segment>
		<Segment><SegStyle>5</SegStyle><End><X>-28.543</X><Y>-15.050</Y></End></Segment>
		<Segment><SegStyle>3</SegStyle><End><X>-29.950</X><Y>-19.380</Y></End></Segment>
		<Segment><SegStyle>5</SegStyle><End><X>-29.950</X><Y>-19.154</Y></End></Segment>
		<Segment><SegStyle>3</SegStyle><End><X>-28.617</X><Y>-15.050</Y></End></Segment>
		<Segment><SegStyle>5</SegStyle><End><X>-28.690</X><Y>-15.050</Y></End></Segment>
		<Segment><SegStyle>3</SegStyle><End><X>-29.950</X><Y>-18.927</Y></End></Segment>
		<Segment><SegStyle>5</SegStyle><End><X>-29.950</X><Y>-18.701</Y></End></Segment>
		<Segment><SegStyle>3</SegStyle><End><X>-28.764</X><Y>-15.050</Y></End></Segment>
		<Segment><SegStyle>5</SegStyle><End><X>-28.837</X><Y>-15.050</Y></End></Segment>
		<Segment><SegStyle>3</SegStyle><End><X>-29.950</X><Y>-18.474</Y></End></Segment>
		<Segment><SegStyle>5</SegStyle><End><X>-29.950</X><Y>-18.248</Y></End></Segment>
		<Segment><SegStyle>3</SegStyle><End><X>-28.911</X><Y>-15.050</Y></End></Segment>
		<Segment><SegStyle>5</SegStyle><End><X>-28.985</X><Y>-15.050</Y></End></Segment>
		<Segment><SegStyle>3</SegStyle><End><X>-29.950</X><Y>-18.021</Y></End></Segment>
		<Segment><SegStyle>5</SegStyle><End><X>-29.950</X><Y>-17.795</Y></End></Segment>
		<Segment><SegStyle>3</SegStyle><End><X>-29.058</X><Y>-15.050</Y></End></Segment>
		<Segment><SegStyle>5</SegStyle><End><X>-29.132</X><Y>-15.050</Y></End></Segment>
		<Segment><SegStyle>3</SegStyle><End><X>-29.950</X><Y>-17.568</Y></End></Segment>
		<Segment><SegStyle>5</SegStyle><End><X>-29.950</X><Y>-17.341</Y></End></Segment>
		<Segment><SegStyle>3</SegStyle><End><X>-29.205</X><Y>-15.050</Y></End></Segment>
		<Segment><SegStyle>5</SegStyle><End><X>-29.279</X><Y>-15.050</Y></End></Segment>
		<Segment><SegStyle>3</SegStyle><End><X>-29.950</X><Y>-17.115</Y></End></Segment>
		<Segment><SegStyle>5</SegStyle><End><X>-29.950</X><Y>-16.888</Y></End></Segment>
		<Segment><SegStyle>3</SegStyle><End><X>-29.353</X><Y>-15.050</Y></End></Segment>
		<Segment><SegStyle>5</SegStyle><End><X>-29.426</X><Y>-15.050</Y></End></Segment>
		<Segment><SegStyle>3</SegStyle><End><X>-29.950</X><Y>-16.662</Y></End></Segment>
		<Segment><SegStyle>5</SegStyle><End><X>-29.950</X><Y>-16.435</Y></End></Segment>
		<Segment><SegStyle>3</SegStyle><End><X>-29.500</X><Y>-15.050</Y></End></Segment>
		<Segment><SegStyle>5</SegStyle><End><X>-29.573</X><Y>-15.050</Y></End></Segment>
		<Segment><SegStyle>3</SegStyle><End><X>-29.950</X><Y>-16.209</Y></End></Segment>
		<Segment><SegStyle>5</SegStyle><End><X>-29.950</X><Y>-15.982</Y></End></Segment>
		<Segment><SegStyle>3</SegStyle><End><X>-29.647</X><Y>-15.050</Y></End></Segment>
		<Segment><SegStyle>5</SegStyle><End><X>-29.721</X><Y>-15.050</Y></End></Segment>
		<Segment><SegStyle>3</SegStyle><End><X>-29.950</X><Y>-15.756</Y></End></Segment>
		<Segment><SegStyle>5</SegStyle><End><X>-29.950</X><Y>-15.529</Y></End></Segment>
		<Segment><SegStyle>3</SegStyle><End><X>-29.794</X><Y>-15.050</Y></End></Segment>
		<Segment><SegStyle>5</SegStyle><End><X>-29.868</X><Y>-15.050</Y></End></Segment>
		<Segment><SegStyle>3</SegStyle><End><X>-29.950</X><Y>-15.303</Y></End></Segment>
		<Segment><SegStyle>5</SegStyle><End><X>-29.950</X><Y>-15.076</Y></End></Segment>
		<Segment><SegStyle>3</SegStyle><End><X>-29.941</X><Y>-15.050</Y></End></Segment></Path>
	<Path>
		<Type>hatch</Type>
		<Tag>pyramid</Tag>
		<NumSegments>423</NumSegments>
		<SkyWritingMode>1</SkyWritingMode>
		<Start><X>-14.748</X><Y>30.190</Y></Start>
		<Segment><SegStyle>4</SegStyle><End><X>-14.669</X><Y>30.432</Y></End></Segment>
		<Segment><SegStyle>6</SegStyle><End><X>-14.669</X><Y>30.724</Y></End></Segment>
		<Segment><SegStyle>4</SegStyle><End><X>-14.843</X><Y>30.190</Y></End></Segment>
		<Segment><SegStyle>6</SegStyle><End><X>-14.937</X><Y>30.190</Y></End></Segment>
		<Segment><SegStyle>4</SegStyle><End><X>-14.669</X><Y>31.015</Y></End></Segment>
		<Segment><SegStyle>6</SegStyle><End><X>-14.669</X><Y>31.306</Y></End></Segment>
		<Segment><SegStyle>4</SegStyle><End><X>-15.032</X><Y>30.190</Y></End></Segment>
		<Segment><SegStyle>6</SegStyle><End><X>-15.126</X><Y>30.190</Y></End></Segment>
		<Segment><SegStyle>4</SegStyle><End><X>-14.669</X><Y>31.597</Y></End></Segment>
		<Segment><SegStyle>6</SegStyle><End><X>-14.669</X><Y>31.889</Y></End></Segment>
		<Segment><SegStyle>4</SegStyle><End><X>-15.221</X><Y>30.190</Y></End></Segment>
		<Segment><SegStyle>6</SegStyle><End><X>-15.316</X><Y>30.190</Y></End></Segment>
		<Segment><SegStyle>4</SegStyle><End><X>-14.669</X><Y>32.180</Y></End></Segment>
		<Segment><SegStyle>6</SegStyle><End><X>-14.669</X><Y>32.471</Y></End></Segment>
		<Segment><SegStyle>4</SegStyle><End><X>-15.410</X><Y>30.190</Y></End></Segment>
		<Segment><SegStyle>6</SegStyle><End><X>-15.505</X><Y>30.190</Y></End></Segment>
		<Segment><SegStyle>4</SegStyle><End><X>-14.669</X><Y>32.762</Y></End></Segment>
		<Segment><SegStyle>6</SegStyle><End><X>-14.669</X><Y>33.054</Y></End></Segment>
		<Segment><SegStyle>4</SegStyle><End><X>-15.600</X><Y>30.190</Y></End></Segment>
		<Segment><SegStyle>6</SegStyle><End><X>-15.694</X><Y>30.190</Y></End></Segment>
		<Segment><SegStyle>4</SegStyle><End><X>-14.669</X><Y>33.345</Y></End></Segment>
		<Segment><SegStyle>6</SegStyle><End><X>-14.669</X><Y>33.636</Y></End></Segment>
		<Segment><SegStyle>4</SegStyle><End><X>-15.789</X><Y>30.190</Y></End></Segment>
		<Segment><SegStyle>6</SegStyle><End><X>-15.884</X><Y>30.190</Y></End></Segment>
		<Segment><SegStyle>4</SegStyle><End><X>-14.669</X><Y>33.927</Y></End></Segment>
		<Segment><SegStyle>6</SegStyle><End><X>-14.669</X><Y>34.219</Y></End></Segment>
		<Segment><SegStyle>4</SegStyle><End><X>-15.978</X><Y>30.190</Y></End></Segment>
		<Segment><SegStyle>6</SegStyle><End><X>-16.073</X><Y>30.190</Y></End></Segment>
		<Segment><SegStyle>4</SegStyle><End><X>-14.669</X><Y>34.510</Y></End></Segment>
		<Segment><SegStyle>6</SegStyle><End><X>-14.669</X><Y>34.801</Y></End></Segment>
		<Segment><SegStyle>4</SegStyle><End><X>-16.167</X><Y>30.190</Y></End></Segment>
		<Segment><SegStyle>6</SegStyle><End><X>-16.262</X><Y>30.190</Y></End></Segment>
		<Segment><SegStyle>4</SegStyle><End><X>-14.669</X><Y>35.092</Y></End></Segment>
		<Segment><SegStyle>6</SegStyle><End><X>-14.669</X><Y>35.384</Y></End></Segment>
		<Segment><SegStyle>4</SegStyle><End><X>-16.357</X><Y>30.190</Y></End></Segment>
		<Segment><SegStyle>6</SegStyle><End><X>-16.451</X><Y>30.190</Y></End></Segment>
		<Segment><SegStyle>4</SegStyle><End><X>-14.669</X><Y>35.675</Y></End></Segment>
		<Segment><SegStyle>6</SegStyle><End><X>-14.669</X><Y>35.966</Y></End></Segment>
		<Segment><SegStyle>4</SegStyle><End><X>-16.546</X><Y>30.190</Y></End></Segment>
		<Segment><SegStyle>6</SegStyle><End><X>-16.641</X><Y>30.190</Y></End></Segment>
		<Segment><SegStyle>4</SegStyle><End><X>-14.669</X><Y>36.257</Y></End></Segment>
		<Segment><SegStyle>6</SegStyle><End><X>-14.669</X><Y>36.549</Y></End></Segment>
		<Segment><SegStyle>4</SegStyle><End><X>-16.735</X><Y>30.190</Y></End></Segment>
		<Segment><SegStyle>6</SegStyle><End><X>-16.830</X><Y>30.190</Y></End></Segment>
		<Segment><SegStyle>4</SegStyle><End><X>-14.669</X><Y>36.840</Y></End></Segment>
		<Segment><SegStyle>6</SegStyle><End><X>-14.669</X><Y>37.131</Y></End></Segment>
		<Segment><SegStyle>4</SegStyle><End><X>-16.924</X><Y>30.190</Y></End></Segment>
		<Segment><SegStyle>6</SegStyle><End><X>-17.019</X><Y>30.190</Y></End></Segment>
		<Segment><SegStyle>4</SegStyle><End><X>-14.669</X><Y>37.422</Y></End></Segment>
		<Segment><SegStyle>6</SegStyle><End><X>-14.669</X><Y>37.714</Y></End></Segment>
		<Segment><SegStyle>4</SegStyle><End><X>-17.114</X><Y>30.190</Y></End></Segment>
		<Segment><SegStyle>6</SegStyle><End><X>-17.208</X><Y>30.190</Y></End></Segment>
		<Segment><SegStyle>4</SegStyle><End><X>-14.669</X><Y>38.005</Y></End></Segment>
		<Segment><SegStyle>6</SegStyle><End><X>-14.669</X><Y>38.296</Y></End></Segment>
		<Segment><SegStyle>4</SegStyle><End><X>-17.303</X><Y>30.190</Y></End></Segment>
		<Segment><SegStyle>6</SegStyle><End><X>-17.398</X><Y>30.190</Y></End></Segment>
		<Segment><SegStyle>4</SegStyle><End><X>-14.669</X><Y>38.587</Y></End></Segment>
		<Segment><SegStyle>6</SegStyle><End><X>-14.669</X><Y>38.879</Y></End></Segment>
		<Segment><SegStyle>4</SegStyle><End><X>-17.492</X><Y>30.190</Y></End></Segment>
		<Segment><SegStyle>6</SegStyle><End><X>-17.587</X><Y>30.190</Y></End></Segment>
		<Segment><SegStyle>4</SegStyle><End><X>-14.669</X><Y>39.170</Y></End></Segment>
		<Segment><SegStyle>6</SegStyle><End><X>-14.669</X><Y>39.461</Y></End></Segment>
		<Segment><SegStyle>4</SegStyle><End><X>-17.682</X><Y>30.190</Y></End></Segment>
		<Segment><SegStyle>6</SegStyle><End><X>-17.776</X><Y>30.190</Y></End></Segment>
		<Segment><SegStyle>4</SegStyle><End><X>-14.669</X><Y>39.752</Y></End></Segment>
		<Segment><SegStyle>6</SegStyle><End><X>-14.669</X><Y>40.044</Y></End></Segment>
		<Segment><SegStyle>4</SegStyle><End><X>-17.871</X><Y>30.190</Y></End></Segment>
		<Segment><SegStyle>6</SegStyle><End><X>-17.965</X><Y>30.190</Y></End></Segment>
		<Segment><SegStyle>4</SegStyle><End><X>-14.669</X><Y>40.335</Y></End></Segment>
		<Segment><SegStyle>6</SegStyle><End><X>-14.669</X><Y>40.626</Y></End></Segment>
		<Segment><SegStyle>4</SegStyle><End><X>-18.060</X><Y>30.190</Y></End></Segment>
		<Segment><SegStyle>6</SegStyle><End><X>-18.155</X><Y>30.190</Y></End></Segment>
		<Segment><SegStyle>4</SegStyle><End><X>-14.669</X><Y>40.917</Y></End></Segment>
		<Segment><SegStyle>6</SegStyle><End><X>-14.669</X><Y>41.209</Y></End></Segment>
		<Segment><SegStyle>4</SegStyle><End><X>-18.249</X><Y>30.190</Y></End></Segment>
		<Segment><SegStyle>6</SegStyle><End><X>-18.344</X><Y>30.190</Y></End></Segment>
		<Segment><SegStyle>4</SegStyle><End><X>-14.669</X><Y>41.500</Y></End></Segment>
		<Segment><SegStyle>6</SegStyle><End><X>-14.669</X><Y>41.791</Y></End></Segment>
		<Segment><SegStyle>4</SegStyle><End><X>-18.439</X><Y>30.190</Y></End></Segment>
		<Segment><SegStyle>6</SegStyle><End><X>-18.533</X><Y>30.190</Y></End></Segment>
		<Segment><SegStyle>4</SegStyle><End><X>-14.669</X><Y>42.082</Y></End></Segment>
		<Segment><SegStyle>6</SegStyle><End><X>-14.669</X><Y>42.374</Y></End></Segment>
		<Segment><SegStyle>4</SegStyle><End><X>-18.628</X><Y>30.190</Y></End></Segment>
		<Segment><SegStyle>6</SegStyle><End><X>-18.722</X><Y>30.190</Y></End></Segment>
		<Segment><SegStyle>4</SegStyle><End><X>-14.669</X><Y>42.665</Y></End></Segment>
		<Segment><SegStyle>6</SegStyle><End><X>-14.669</X><Y>42.956</Y></End></Segment>
		<Segment><SegStyle>4</SegStyle><End><X>-18.817</X><Y>30.190</Y></End></Segment>
		<Segment><SegStyle>6</SegStyle><End><X>-18.912</X><Y>30.190</Y></End></Segment>
		<Segment><SegStyle>4</SegStyle><End><X>-14.669</X><Y>43.247</Y></End></Segment>
		<Segment><SegStyle>6</SegStyle><End><X>-14.669</X><Y>43.539</Y></End></Segment>
		<Segment><SegStyle>4</SegStyle><End><X>-19.006</X><Y>30.190</Y></End></Segment>
		<Segment><SegStyle>6</SegStyle><End><X>-19.101</X><Y>30.190</Y></End></Segment>
		<Segment><SegStyle>4</SegStyle><End><X>-14.669</X><Y>43.830</Y></End></Segment>
		<Segment><SegStyle>6</SegStyle><End><X>-14.669</X><Y>44.121</Y></End></Segment>
		<Segment><SegStyle>4</SegStyle><End><X>-19.196</X><Y>30.190</Y></End></Segment>
		<Segment><SegStyle>6</SegStyle><End><X>-19.290</X><Y>30.190</Y></End></Segment>
		<Segment><SegStyle>4</SegStyle><End><X>-14.669</X><Y>44.412</Y></End></Segment>
		<Segment><SegStyle>6</SegStyle><End><X>-14.669</X><Y>44.703</Y></End></Segment>
		<Segment><SegStyle>4</SegStyle><End><X>-19.385</X><Y>30.190</Y></End></Segment>
		<Segment><SegStyle>6</SegStyle><End><X>-19.480</X><Y>30.190</Y></End></Segment>
		<Segment><SegStyle>4</SegStyle><End><X>-14.669</X><Y>44.995</Y></End></Segment>
		<Segment><SegStyle>6</SegStyle><End><X>-14.669</X><Y>45.286</Y></End></Segment>
		<Segment><SegStyle>4</SegStyle><End><X>-19.574</X><Y>30.190</Y></End></Segment>
		<Segment><SegStyle>6</SegStyle><End><X>-19.669</X><Y>30.190</Y></End></Segment>
		<Segment><SegStyle>4</SegStyle><End><X>-14.749</X><Y>45.331</Y></End></Segment>
		<Segment><SegStyle>6</SegStyle><End><X>-14.844</X><Y>45.331</Y></End></Segment>
		<Segment><SegStyle>4</SegStyle><End><X>-19.763</X><Y>30.190</Y></End></Segment>
		<Segment><SegStyle>6</SegStyle><End><X>-19.858</X><Y>30.190</Y></End></Segment>
		<Segment><SegStyle>4</SegStyle><End><X>-14.938</X><Y>45.331</Y></End></Segment>
		<Segment><SegStyle>6</SegStyle><End><X>-15.033</X><Y>45.331</Y></End></Segment>
		<Segment><SegStyle>4</SegStyle><End><X>-19.953</X><Y>30.190</Y></End></Segment>
		<Segment><SegStyle>6</SegStyle><End><X>-20.047</X><Y>30.190</Y></End></Segment>
		<Segment><SegStyle>4</SegStyle><End><X>-15.128</X><Y>45.331</Y></End></Segment>
		<Segment><SegStyle>6</SegStyle><End><X>-15.222</X><Y>45.331</Y></End></Segment>
		<Segment><SegStyle>4</SegStyle><End><X>-20.142</X><Y>30.190</Y></End></Segment>
		<Segment><SegStyle>6</SegStyle><End><X>-20.237</X><Y>30.190</Y></End></Segment>
		<Segment><SegStyle>4</SegStyle><End><X>-15.317</X><Y>45.331</Y></End></Segment>
		<Segment><SegStyle>6</SegStyle><End><X>-15.412</X><Y>45.331</Y></End></Segment>
		<Segment><SegStyle>4</SegStyle><End><X>-20.331</X><Y>30.190</Y></End></Segment>
		<Segment><SegStyle>6</SegStyle><End><X>-20.426</X><Y>30.190</Y></End></Segment>
		<Segment><SegStyle>4</SegStyle><End><X>-15.506</X><Y>45.331</Y></End></Segment>
		<Segment><SegStyle>6</SegStyle><End><X>-15.601</X><Y>45.331</Y></End></Segment>
		<Segment><SegStyle>4</SegStyle><End><X>-20.520</X><Y>30.190</Y></End></Segment>
		<Segment><SegStyle>6</SegStyle><End><X>-20.615</X><Y>30.190</Y></End></Segment>
		<Segment><SegStyle>4</SegStyle><End><X>-15.696</X><Y>45.331</Y></End></Segment>
		<Segment><SegStyle>6</SegStyle><End><X>-15.790</X><Y>45.331</Y></End></Segment>
		<Segment><SegStyle>4</SegStyle><End><X>-20.710</X><Y>30.190</Y></End></Segment>
		<Segment><SegStyle>6</SegStyle><End><X>-20.804</X><Y>30.190</Y></End></Segment>
		<Segment><SegStyle>4</SegStyle><End><X>-15.885</X><Y>45.331</Y></End></Segment>
		<Segment><SegStyle>6</SegStyle><End><X>-15.979</X><Y>45.331</Y></End></Segment>
		<Segment><SegStyle>4</SegStyle><End><X>-20.899</X><Y>30.190</Y></End></Segment>
		<Segment><SegStyle>6</SegStyle><End><X>-20.994</X><Y>30.190</Y></End></Segment>
		<Segment><SegStyle>4</SegStyle><End><X>-16.074</X><Y>45.331</Y></End></Segment>
		<Segment><SegStyle>6</SegStyle><End><X>-16.169</X><Y>45.331</Y></End></Segment>
		<Segment><SegStyle>4</SegStyle><End><X>-21.088</X><Y>30.190</Y></End></Segment>
		<Segment><SegStyle>6</SegStyle><End><X>-21.183</X><Y>30.190</Y></End></Segment>
		<Segment><SegStyle>4</SegStyle><End><X>-16.263</X><Y>45.331</Y></End></Segment>
		<Segment><SegStyle>6</SegStyle><End><X>-16.358</X><Y>45.331</Y></End></Segment>
		<Segment><SegStyle>4</SegStyle><End><X>-21.278</X><Y>30.190</Y></End></Segment>
		<Segment><SegStyle>6</SegStyle><End><X>-21.372</X><Y>30.190</Y></End></Segment>
		<Segment><SegStyle>4</SegStyle><End><X>-16.453</X><Y>45.331</Y></End></Segment>
		<Segment><SegStyle>6</SegStyle><End><X>-16.547</X><Y>45.331</Y></End></Segment>
		<Segment><SegStyle>4</SegStyle><End><X>-21.467</X><Y>30.190</Y></End></Segment>
		<Segment><SegStyle>6</SegStyle><End><X>-21.561</X><Y>30.190</Y></End></Segment>
		<Segment><SegStyle>4</SegStyle><End><X>-16.642</X><Y>45.331</Y></End></Segment>
		<Segment><SegStyle>6</SegStyle><End><X>-16.736</X><Y>45.331</Y></End></Segment>
		<Segment><SegStyle>4</SegStyle><End><X>-21.656</X><Y>30.190</Y></End></Segment>
		<Segment><SegStyle>6</SegStyle><End><X>-21.751</X><Y>30.190</Y></End></Segment>
		<Segment><SegStyle>4</SegStyle><End><X>-16.831</X><Y>45.331</Y></End></Segment>
		<Segment><SegStyle>6</SegStyle><End><X>-16.926</X><Y>45.331</Y></End></Segment>
		<Segment><SegStyle>4</SegStyle><End><X>-21.845</X><Y>30.190</Y></End></Segment>
		<Segment><SegStyle>6</SegStyle><End><X>-21.940</X><Y>30.190</Y></End></Segment>
		<Segment><SegStyle>4</SegStyle><End><X>-17.020</X><Y>45.331</Y></End></Segment>
		<Segment><SegStyle>6</SegStyle><End><X>-17.115</X><Y>45.331</Y></End></Segment>
		<Segment><SegStyle>4</SegStyle><End><X>-22.035</X><Y>30.190</Y></End></Segment>
		<Segment><SegStyle>6</SegStyle><End><X>-22.129</X><Y>30.190</Y></End></Segment>
		<Segment><SegStyle>4</SegStyle><End><X>-17.210</X><Y>45.331</Y></End></Segment>
		<Segment><SegStyle>6</SegStyle><End><X>-17.304</X><Y>45.331</Y></End></Segment>
		<Segment><SegStyle>4</SegStyle><End><X>-22.224</X><Y>30.190</Y></End></Segment>
		<Segment><SegStyle>6</SegStyle><End><X>-22.318</X><Y>30.190</Y></End></Segment>
		<Segment><SegStyle>4</SegStyle><End><X>-17.399</X><Y>45.331</Y></End></Segment>
		<Segment><SegStyle>6</SegStyle><End><X>-17.494</X><Y>45.331</Y></End></Segment>
		<Segment><SegStyle>4</SegStyle><End><X>-22.413</X><Y>30.190</Y></End></Segment>
		<Segment><SegStyle>6</SegStyle><End><X>-22.508</X><Y>30.190</Y></End></Segment>
		<Segment><SegStyle>4</SegStyle><End><X>-17.588</X><Y>45.331</Y></End></Segment>
		<Segment><SegStyle>6</SegStyle><End><X>-17.683</X><Y>45.331</Y></End></Segment>
		<Segment><SegStyle>4</SegStyle><End><X>-22.602</X><Y>30.190</Y></End></Segment>
		<Segment><SegStyle>6</SegStyle><End><X>-22.697</X><Y>30.190</Y></End></Segment>
		<Segment><SegStyle>4</SegStyle><End><X>-17.777</X><Y>45.331</Y></End></Segment>
		<Segment><SegStyle>6</SegStyle><End><X>-17.872</X><Y>45.331</Y></End></Segment>
		<Segment><SegStyle>4</SegStyle><End><X>-22.792</X><Y>30.190</Y></End></Segment>
		<Segment><SegStyle>6</SegStyle><End><X>-22.886</X><Y>30.190</Y></End></Segment>
		<Segment><SegStyle>4</SegStyle><End><X>-17.967</X><Y>45.331</Y></End></Segment>
		<Segment><SegStyle>6</SegStyle><End><X>-18.061</X><Y>45.331</Y></End></Segment>
		<Segment><SegStyle>4</SegStyle><End><X>-22.981</X><Y>30.190</Y></End></Segment>
		<Segment><SegStyle>6</SegStyle><End><X>-23.076</X><Y>30.190</Y></End></Segment>
		<Segment><SegStyle>4</SegStyle><End><X>-18.156</X><Y>45.331</Y></End></Segment>
		<Segment><SegStyle>6</SegStyle><End><X>-18.251</X><Y>45.331</Y></End></Segment>
		<Segment><SegStyle>4</SegStyle><End><X>-23.170</X><Y>30.190</Y></End></Segment>
		<Segment><SegStyle>6</SegStyle><End><X>-23.265</X><Y>30.190</Y></End></Segment>
		<Segment><SegStyle>4</SegStyle><End><X>-18.345</X><Y>45.331</Y></End></Segment>
		<Segment><SegStyle>6</SegStyle><End><X>-18.440</X><Y>45.331</Y></End></Segment>
		<Segment><SegStyle>4</SegStyle><End><X>-23.359</X><Y>30.190</Y></End></Segment>
		<Segment><SegStyle>6</SegStyle><End><X>-23.454</X><Y>30.190</Y></End></Segment>
		<Segment><SegStyle>4</SegStyle><End><X>-18.534</X><Y>45.331</Y></End></Segment>
		<Segment><SegStyle>6</SegStyle><End><X>-18.629</X><Y>45.331</Y></End></Segment>
		<Segment><SegStyle>4</SegStyle><End><X>-23.549</X><Y>30.190</Y></End></Segment>
		<Segment><SegStyle>6</SegStyle><End><X>-23.643</X><Y>30.190</Y></End></Segment>
		<Segment><SegStyle>4</SegStyle><End><X>-18.724</X><Y>45.331</Y></End></Segment>
		<Segment><SegStyle>6</SegStyle><End><X>-18.818</X><Y>45.331</Y></End></Segment>
		<Segment><SegStyle>4</SegStyle><End><X>-23.738</X><Y>30.190</Y></End></Segment>
		<Segment><SegStyle>6</SegStyle><End><X>-23.833</X><Y>30.190</Y></End></Segment>
		<Segment><SegStyle>4</SegStyle><End><X>-18.913</X><Y>45.331</Y></End></Segment>
		<Segment><SegStyle>6</SegStyle><End><X>-19.008</X><Y>45.331</Y></End></Segment>
		<Segment><SegStyle>4</SegStyle><End><X>-23.927</X><Y>30.190</Y></End></Segment>
		<Segment><SegStyle>6</SegStyle><End><X>-24.022</X><Y>30.190</Y></End></Segment>
		<Segment><SegStyle>4</SegStyle><End><X>-19.102</X><Y>45.331</Y></End></Segment>
		<Segment><SegStyle>6</SegStyle><End><X>-19.197</X><Y>45.331</Y></End></Segment>
		<Segment><SegStyle>4</SegStyle><End><X>-24.116</X><Y>30.190</Y></End></Segment>
		<Segment><SegStyle>6</SegStyle><End><X>-24.211</X><Y>30.190</Y></End></Segment>
		<Segment><SegStyle>4</SegStyle><End><X>-19.292</X><Y>45.331</Y></End></Segment>
		<Segment><SegStyle>6</SegStyle><End><X>-19.386</X><Y>45.331</Y></End></Segment>
		<Segment><SegStyle>4</SegStyle><End><X>-24.306</X><Y>30.190</Y></End></Segment>
		<Segment><SegStyle>6</SegStyle><End><X>-24.400</X><Y>30.190</Y></End></Segment>
		<Segment><SegStyle>4</SegStyle><End><X>-19.481</X><Y>45.331</Y></End></Segment>
		<Segment><SegStyle>6</SegStyle><End><X>-19.575</X><Y>45.331</Y></End></Segment>
		<Segment><SegStyle>4</SegStyle><End><X>-24.495</X><Y>30.190</Y></End></Segment>
		<Segment><SegStyle>6</SegStyle><End><X>-24.590</X><Y>30.190</Y></End></Segment>
		<Segment><SegStyle>4</SegStyle><End><X>-19.670</X><Y>45.331</Y></End></Segment>
		<Segment><SegStyle>6</SegStyle><End><X>-19.765</X><Y>45.331</Y></End></Segment>
		<Segment><SegStyle>4</SegStyle><End><X>-24.684</X><Y>30.190</Y></End></Segment>
		<Segment><SegStyle>6</SegStyle><End><X>-24.779</X><Y>30.190</Y></End></Segment>
		<Segment><SegStyle>4</SegStyle><End><X>-19.859</X><Y>45.331</Y></End></Segment>
		<Segment><SegStyle>6</SegStyle><End><X>-19.954</X><Y>45.331</Y></End></Segment>
		<Segment><SegStyle>4</SegStyle><End><X>-24.874</X><Y>30.190</Y></End></Segment>
		<Segment><SegStyle>6</SegStyle><End><X>-24.968</X><Y>30.190</Y></End></Segment>
		<Segment><SegStyle>4</SegStyle><End><X>-20.049</X><Y>45.331</Y></End></Segment>
		<Segment><SegStyle>6</SegStyle><End><X>-20.143</X><Y>45.331</Y></End></Segment>
		<Segment><SegStyle>4</SegStyle><End><X>-25.063</X><Y>30.190</Y></End></Segment>
		<Segment><SegStyle>6</SegStyle><End><X>-25.157</X><Y>30.190</Y></End></Segment>
		<Segment><SegStyle>4</SegStyle><End><X>-20.238</X><Y>45.331</Y></End></Segment>
		<Segment><SegStyle>6</SegStyle><End><X>-20.332</X><Y>45.331</Y></End></Segment>
		<Segment><SegStyle>4</SegStyle><End><X>-25.252</X><Y>30.190</Y></End></Segment>
		<Segment><SegStyle>6</SegStyle><End><X>-25.347</X><Y>30.190</Y></End></Segment>
		<Segment><SegStyle>4</SegStyle><End><X>-20.427</X><Y>45.331</Y></End></Segment>
		<Segment><SegStyle>6</SegStyle><End><X>-20.522</X><Y>45.331</Y></End></Segment>
		<Segment><SegStyle>4</SegStyle><End><X>-25.441</X><Y>30.190</Y></End></Segment>
		<Segment><SegStyle>6</SegStyle><End><X>-25.536</X><Y>30.190</Y></End></Segment>
		<Segment><SegStyle>4</SegStyle><End><X>-20.616</X><Y>45.331</Y></End></Segment>
		<Segment><SegStyle>6</SegStyle><End><X>-20.711</X><Y>45.331</Y></End></Segment>
		<Segment><SegStyle>4</SegStyle><End><X>-25.631</X><Y>30.190</Y></End></Segment>
		<Segment><SegStyle>6</SegStyle><End><X>-25.725</X><Y>30.190</Y></End></Segment>
		<Segment><SegStyle>4</SegStyle><End><X>-20.806</X><Y>45.331</Y></End></Segment>
		<Segment><SegStyle>6</SegStyle><End><X>-20.900</X><Y>45.331</Y></End></Segment>
		<Segment><SegStyle>4</SegStyle><End><X>-25.820</X><Y>30.190</Y></End></Segment>
		<Segment><SegStyle>6</SegStyle><End><X>-25.914</X><Y>30.190</Y></End></Segment>
		<Segment><SegStyle>4</SegStyle><End><X>-20.995</X><Y>45.331</Y></End></Segment>
		<Segment><SegStyle>6</SegStyle><End><X>-21.090</X><Y>45.331</Y></End></Segment>
		<Segment><SegStyle>4</SegStyle><End><X>-26.009</X><Y>30.190</Y></End></Segment>
		<Segment><SegStyle>6</SegStyle><End><X>-26.104</X><Y>30.190</Y></End></Segment>
		<Segment><SegStyle>4</SegStyle><End><X>-21.184</X><Y>45.331</Y></End></Segment>
		<Segment><SegStyle>6</SegStyle><End><X>-21.279</X><Y>45.331</Y></End></Segment>
		<Segment><SegStyle>4</SegStyle><End><X>-26.198</X><Y>30.190</Y></End></Segment>
		<Segment><SegStyle>6</SegStyle><End><X>-26.293</X><Y>30.190</Y></End></Segment>
		<Segment><SegStyle>4</SegStyle><End><X>-21.373</X><Y>45.331</Y></End></Segment>
		<Segment><SegStyle>6</SegStyle><End><X>-21.468</X><Y>45.331</Y></End></Segment>
		<Segment><SegStyle>4</SegStyle><End><X>-26.388</X><Y>30.190</Y></End></Segment>
		<Segment><SegStyle>6</SegStyle><End><X>-26.482</X><Y>30.190</Y></End></Segment>
		<Segment><SegStyle>4</SegStyle><End><X>-21.563</X><Y>45.331</Y></End></Segment>
		<Segment><SegStyle>6</SegStyle><End><X>-21.657</X><Y>45.331</Y></End></Segment>
		<Segment><SegStyle>4</SegStyle><End><X>-26.577</X><Y>30.190</Y></End></Segment>
		<Segment><SegStyle>6</SegStyle><End><X>-26.672</X><Y>30.190</Y></End></Segment>
		<Segment><SegStyle>4</SegStyle><End><X>-21.752</X><Y>45.331</Y></End></Segment>
		<Segment><SegStyle>6</SegStyle><End><X>-21.847</X><Y>45.331</Y></End></Segment>
		<Segment><SegStyle>4</SegStyle><End><X>-26.766</X><Y>30.190</Y></End></Segment>
		<Segment><SegStyle>6</SegStyle><End><X>-26.861</X><Y>30.190</Y></End></Segment>
		<Segment><SegStyle>4</SegStyle><End><X>-21.941</X><Y>45.331</Y></End></Segment>
		<Segment><SegStyle>6</SegStyle><End><X>-22.036</X><Y>45.331</Y></End></Segment>
		<Segment><SegStyle>4</SegStyle><End><X>-26.955</X><Y>30.190</Y></End></Segment>
		<Segment><SegStyle>6</SegStyle><End><X>-27.050</X><Y>30.190</Y></End></Segment>
		<Segment><SegStyle>4</SegStyle><End><X>-22.130</X><Y>45.331</Y></End></Segment>
		<Segment><SegStyle>6</SegStyle><End><X>-22.225</X><Y>45.331</Y></End></Segment>
		<Segment><SegStyle>4</SegStyle><End><X>-27.145</X><Y>30.190</Y></End></Segment>
		<Segment><SegStyle>6</SegStyle><End><X>-27.239</X><Y>30.190</Y></End></Segment>
		<Segment><SegStyle>4</SegStyle><End><X>-22.320</X><Y>45.331</Y></End></Segment>
		<Segment><SegStyle>6</SegStyle><End><X>-22.414</X><Y>45.331</Y></End></Segment>
		<Segment><SegStyle>4</SegStyle><End><X>-27.334</X><Y>30.190</Y></End></Segment>
		<Segment><SegStyle>6</SegStyle><End><X>-27.429</X><Y>30.190</Y></End></Segment>
		<Segment><SegStyle>4</SegStyle><End><X>-22.509</X><Y>45.331</Y></End></Segment>
		<Segment><SegStyle>6</SegStyle><End><X>-22.604</X><Y>45.331</Y></End></Segment>
		<Segment><SegStyle>4</SegStyle><End><X>-27.523</X><Y>30.190</Y></End></Segment>
		<Segment><SegStyle>6</SegStyle><End><X>-27.618</X><Y>30.190</Y></End></Segment>
		<Segment><SegStyle>4</SegStyle><End><X>-22.698</X><Y>45.331</Y></End></Segment>
		<Segment><SegStyle>6</SegStyle><End><X>-22.793</X><Y>45.331</Y></End></Segment>
		<Segment><SegStyle>4</SegStyle><End><X>-27.712</X><Y>30.190</Y></End></Segment>
		<Segment><SegStyle>6</SegStyle><End><X>-27.807</X><Y>30.190</Y></End></Segment>
		<Segment><SegStyle>4</SegStyle><End><X>-22.888</X><Y>45.331</Y></End></Segment>
		<Segment><SegStyle>6</SegStyle><End><X>-22.982</X><Y>45.331</Y></End></Segment>
		<Segment><SegStyle>4</SegStyle><End><X>-27.902</X><Y>30.190</Y></End></Segment>
		<Segment><SegStyle>6</SegStyle><End><X>-27.996</X><Y>30.190</Y></End></Segment>
		<Segment><SegStyle>4</SegStyle><End><X>-23.077</X><Y>45.331</Y></End></Segment>
		<Segment><SegStyle>6</SegStyle><End><X>-23.171</X><Y>45.331</Y></End></Segment>
		<Segment><SegStyle>4</SegStyle><End><X>-28.091</X><Y>30.190</Y></End></Segment>
		<Segment><SegStyle>6</SegStyle><End><X>-28.186</X><Y>30.190</Y></End></Segment>
		<Segment><SegStyle>4</SegStyle><End><X>-23.266</X><Y>45.331</Y></End></Segment>
		<Segment><SegStyle>6</SegStyle><End><X>-23.361</X><Y>45.331</Y></End></Segment>
		<Segment><SegStyle>4</SegStyle><End><X>-28.280</X><Y>30.190</Y></End></Segment>
		<Segment><SegStyle>6</SegStyle><End><X>-28.375</X><Y>30.190</Y></End></Segment>
		<Segment><SegStyle>4</SegStyle><End><X>-23.455</X><Y>45.331</Y></End></Segment>
		<Segment><SegStyle>6</SegStyle><End><X>-23.550</X><Y>45.331</Y></End></Segment>
		<Segment><SegStyle>4</SegStyle><End><X>-28.470</X><Y>30.190</Y></End></Segment>
		<Segment><SegStyle>6</SegStyle><End><X>-28.564</X><Y>30.190</Y></End></Segment>
		<Segment><SegStyle>4</SegStyle><End><X>-23.645</X><Y>45.331</Y></End></Segment>
		<Segment><SegStyle>6</SegStyle><End><X>-23.739</X><Y>45.331</Y></End></Segment>
		<Segment><SegStyle>4</SegStyle><End><X>-28.659</X><Y>30.190</Y></End></Segment>
		<Segment><SegStyle>6</SegStyle><End><X>-28.753</X><Y>30.190</Y></End></Segment>
		<Segment><SegStyle>4</SegStyle><End><X>-23.834</X><Y>45.331</Y></End></Segment>
		<Segment><SegStyle>6</SegStyle><End><X>-23.928</X><Y>45.331</Y></End></Segment>
		<Segment><SegStyle>4</SegStyle><End><X>-28.848</X><Y>30.190</Y></End></Segment>
		<Segment><SegStyle>6</SegStyle><End><X>-28.943</X><Y>30.190</Y></End></Segment>
		<Segment><SegStyle>4</SegStyle><End><X>-24.023</X><Y>45.331</Y></End></Segment>
		<Segment><SegStyle>6</SegStyle><End><X>-24.118</X><Y>45.331</Y></End></Segment>
		<Segment><SegStyle>4</SegStyle><End><X>-29.037</X><Y>30.190</Y></End></Segment>
		<Segment><SegStyle>6</SegStyle><End><X>-29.132</X><Y>30.190</Y></End></Segment>
		<Segment><SegStyle>4</SegStyle><End><X>-24.212</X><Y>45.331</Y></End></Segment>
		<Segment><SegStyle>6</SegStyle><End><X>-24.307</X><Y>45.331</Y></End></Segment>
		<Segment><SegStyle>4</SegStyle><End><X>-29.227</X><Y>30.190</Y></End></Segment>
		<Segment><SegStyle>6</SegStyle><End><X>-29.321</X><Y>30.190</Y></End></Segment>
		<Segment><SegStyle>4</SegStyle><End><X>-24.402</X><Y>45.331</Y></End></Segment>
		<Segment><SegStyle>6</SegStyle><End><X>-24.496</X><Y>45.331</Y></End></Segment>
		<Segment><SegStyle>4</SegStyle><End><X>-29.416</X><Y>30.190</Y></End></Segment>
		<Segment><SegStyle>6</SegStyle><End><X>-29.510</X><Y>30.190</Y></End></Segment>
		<Segment><SegStyle>4</SegStyle><End><X>-24.591</X><Y>45.331</Y></End></Segment>
		<Segment><SegStyle>6</SegStyle><End><X>-24.686</X><Y>45.331</Y></End></Segment>
		<Segment><SegStyle>4</SegStyle><End><X>-29.605</X><Y>30.190</Y></End></Segment>
		<Segment><SegStyle>6</SegStyle><End><X>-29.700</X><Y>30.190</Y></End></Segment>
		<Segment><SegStyle>4</SegStyle><End><X>-24.780</X><Y>45.331</Y></End></Segment>
		<Segment><SegStyle>6</SegStyle><End><X>-24.875</X><Y>45.331</Y></End></Segment>
		<Segment><SegStyle>4</SegStyle><End><X>-29.794</X><Y>30.190</Y></End></Segment>
		<Segment><SegStyle>6</SegStyle><End><X>-29.810</X><Y>30.433</Y></End></Segment>
		<Segment><SegStyle>4</SegStyle><End><X>-24.969</X><Y>45.331</Y></End></Segment>
		<Segment><SegStyle>6</SegStyle><End><X>-25.064</X><Y>45.331</Y></End></Segment>
		<Segment><SegStyle>4</SegStyle><End><X>-29.810</X><Y>30.724</Y></End></Segment>
		<Segment><SegStyle>6</SegStyle><End><X>-29.810</X><Y>31.016</Y></End></Segment>
		<Segment><SegStyle>4</SegStyle><End><X>-25.159</X><Y>45.331</Y></End></Segment>
		<Segment><SegStyle>6</SegStyle><End><X>-25.253</X><Y>45.331</Y></End></Segment>
		<Segment><SegStyle>4</SegStyle><End><X>-29.810</X><Y>31.307</Y></End></Segment>
		<Segment><SegStyle>6</SegStyle><End><X>-29.810</X><Y>31.598</Y></End></Segment>
		<Segment><SegStyle>4</SegStyle><End><X>-25.348</X><Y>45.331</Y></End></Segment>
		<Segment><SegStyle>6</SegStyle><End><X>-25.443</X><Y>45.331</Y></End></Segment>
		<Segment><SegStyle>4</SegStyle><End><X>-29.810</X><Y>31.889</Y></End></Segment>
		<Segment><SegStyle>6</SegStyle><End><X>-29.810</X><Y>32.181</Y></End></Segment>
		<Segment><SegStyle>4</SegStyle><End><X>-25.537</X><Y>45.331</Y></End></Segment>
		<Segment><SegStyle>6</SegStyle><End><X>-25.632</X><Y>45.331</Y></End></Segment>
		<Segment><SegStyle>4</SegStyle><End><X>-29.810</X><Y>32.472</Y></End></Segment>
		<Segment><SegStyle>6</SegStyle><End><X>-29.810</X><Y>32.763</Y></End></Segment>
		<Segment><SegStyle>4</SegStyle><End><X>-25.726</X><Y>45.331</Y></End></Segment>
		<Segment><SegStyle>6</SegStyle><End><X>-25.821</X><Y>45.331</Y></End></Segment>
		<Segment><SegStyle>4</SegStyle><End><X>-29.810</X><Y>33.054</Y></End></Segment>
		<Segment><SegStyle>6</SegStyle><End><X>-29.810</X><Y>33.346</Y></End></Segment>
		<Segment><SegStyle>4</SegStyle><End><X>-25.916</X><Y>45.331</Y></End></Segment>
		<Segment><SegStyle>6</SegStyle><End><X>-26.010</X><Y>45.331</Y></End></Segment>
		<Segment><SegStyle>4</SegStyle><End><X>-29.810</X><Y>33.637</Y></End></Segment>
		<Segment><SegStyle>6</SegStyle><End><X>-29.810</X><Y>33.928</Y></End></Segment>
		<Segment><SegStyle>4</SegStyle><End><X>-26.105</X><Y>45.331</Y></End></Segment>
		<Segment><SegStyle>6</SegStyle><End><X>-26.200</X><Y>45.331</Y></End></Segment>
		<Segment><SegStyle>4</SegStyle><End><X>-29.810</X><Y>34.219</Y></End></Segment>
		<Segment><SegStyle>6</SegStyle><End><X>-29.810</X><Y>34.511</Y></End></Segment>
		<Segment><SegStyle>4</SegStyle><End><X>-26.294</X><Y>45.331</Y></End></Segment>
		<Segment><SegStyle>6</SegStyle><End><X>-26.389</X><Y>45.331</Y></End></Segment>
		<Segment><SegStyle>4</SegStyle><End><X>-29.810</X><Y>34.802</Y></End></Segment>
		<Segment><SegStyle>6</SegStyle><End><X>-29.810</X><Y>35.093</Y></End></Segment>
		<Segment><SegStyle>4</SegStyle><End><X>-26.484</X><Y>45.331</Y></End></Segment>
		<Segment><SegStyle>6</SegStyle><End><X>-26.578</X><Y>45.331</Y></End></Segment>
		<Segment><SegStyle>4</SegStyle><End><X>-29.810</X><Y>35.384</Y></End></Segment>
		<Segment><SegStyle>6</SegStyle><End><X>-29.810</X><Y>35.676</Y></End></Segment>
		<Segment><SegStyle>4</SegStyle><End><X>-26.673</X><Y>45.331</Y></End></Segment>
		<Segment><SegStyle>6</SegStyle><End><X>-26.767</X><Y>45.331</Y></End></Segment>
		<Segment><SegStyle>4</SegStyle><End><X>-29.810</X><Y>35.967</Y></End></Segment>
		<Segment><SegStyle>6</SegStyle><End><X>-29.810</X><Y>36.258</Y></End></Segment>
		<Segment><SegStyle>4</SegStyle><End><X>-26.862</X><Y>45.331</Y></End></Segment>
		<Segment><SegStyle>6</SegStyle><End><X>-26.957</X><Y>45.331</Y></End></Segment>
		<Segment><SegStyle>4</SegStyle><End><X>-29.810</X><Y>36.549</Y></End></Segment>
		<Segment><SegStyle>6</SegStyle><End><X>-29.810</X><Y>36.841</Y></End></Segment>
		<Segment><SegStyle>4</SegStyle><End><X>-27.051</X><Y>45.331</Y></End></Segment>
		<Segment><SegStyle>6</SegStyle><End><X>-27.146</X><Y>45.331</Y></End></Segment>
		<Segment><SegStyle>4</SegStyle><End><X>-29.810</X><Y>37.132</Y></End></Segment>
		<Segment><SegStyle>6</SegStyle><End><X>-29.810</X><Y>37.423</Y></End></Segment>
		<Segment><SegStyle>4</SegStyle><End><X>-27.241</X><Y>45.331</Y></End></Segment>
		<Segment><SegStyle>6</SegStyle><End><X>-27.335</X><Y>45.331</Y></End></Segment>
		<Segment><SegStyle>4</SegStyle><End><X>-29.810</X><Y>37.714</Y></End></Segment>
		<Segment><SegStyle>6</SegStyle><End><X>-29.810</X><Y>38.005</Y></End></Segment>
		<Segment><SegStyle>4</SegStyle><End><X>-27.430</X><Y>45.331</Y></End></Segment>
		<Segment><SegStyle>6</SegStyle><End><X>-27.524</X><Y>45.331</Y></End></Segment>
		<Segment><SegStyle>4</SegStyle><End><X>-29.810</X><Y>38.297</Y></End></Segment>
		<Segment><SegStyle>6</SegStyle><End><X>-29.810</X><Y>38.588</Y></End></Segment>
		<Segment><SegStyle>4</SegStyle><End><X>-27.619</X><Y>45.331</Y></End></Segment>
		<Segment><SegStyle>6</SegStyle><End><X>-27.714</X><Y>45.331</Y></End></Segment>
		<Segment><SegStyle>4</SegStyle><End><X>-29.810</X><Y>38.879</Y></End></Segment>
		<Segment><SegStyle>6</SegStyle><End><X>-29.810</X><Y>39.170</Y></End></Segment>
		<Segment><SegStyle>4</SegStyle><End><X>-27.808</X><Y>45.331</Y></End></Segment>
		<Segment><SegStyle>6</SegStyle><End><X>-27.903</X><Y>45.331</Y></End></Segment>
		<Segment><SegStyle>4</SegStyle><End><X>-29.810</X><Y>39.462</Y></End></Segment>
		<Segment><SegStyle>6</SegStyle><End><X>-29.810</X><Y>39.753</Y></End></Segment>
		<Segment><SegStyle>4</SegStyle><End><X>-27.998</X><Y>45.331</Y></End></Segment>
		<Segment><SegStyle>6</SegStyle><End><X>-28.092</X><Y>45.331</Y></End></Segment>
		<Segment><SegStyle>4</SegStyle><End><X>-29.810</X><Y>40.044</Y></End></Segment>
		<Segment><SegStyle>6</SegStyle><End><X>-29.810</X><Y>40.335</Y></End></Segment>
		<Segment><SegStyle>4</SegStyle><End><X>-28.187</X><Y>45.331</Y></End></Segment>
		<Segment><SegStyle>6</SegStyle><End><X>-28.282</X><Y>45.331</Y></End></Segment>
		<Segment><SegStyle>4</SegStyle><End><X>-29.810</X><Y>40.627</Y></End></Segment>
		<Segment><SegStyle>6</SegStyle><End><X>-29.810</X><Y>40.918</Y></End></Segment>
		<Segment><SegStyle>4</SegStyle><End><X>-28.376</X><Y>45.331</Y></End></Segment>
		<Segment><SegStyle>6</SegStyle><End><X>-28.471</X><Y>45.331</Y></End></Segment>
		<Segment><SegStyle>4</SegStyle><End><X>-29.810</X><Y>41.209</Y></End></Segment>
		<Segment><SegStyle>6</SegStyle><End><X>-29.810</X><Y>41.500</Y></End></Segment>
		<Segment><SegStyle>4</SegStyle><End><X>-28.565</X><Y>45.331</Y></End></Segment>
		<Segment><SegStyle>6</SegStyle><End><X>-28.660</X><Y>45.331</Y></End></Segment>
		<Segment><SegStyle>4</SegStyle><End><X>-29.810</X><Y>41.792</Y></End></Segment>
		<Segment><SegStyle>6</SegStyle><End><X>-29.810</X><Y>42.083</Y></End></Segment>
		<Segment><SegStyle>4</SegStyle><End><X>-28.755</X><Y>45.331</Y></End></Segment>
		<Segment><SegStyle>6</SegStyle><End><X>-28.849</X><Y>45.331</Y></End></Segment>
		<Segment><SegStyle>4</SegStyle><End><X>-29.810</X><Y>42.374</Y></End></Segment>
		<Segment><SegStyle>6</SegStyle><End><X>-29.810</X><Y>42.665</Y></End></Segment>
		<Segment><SegStyle>4</SegStyle><End><X>-28.944</X><Y>45.331</Y></End></Segment>
		<Segment><SegStyle>6</SegStyle><End><X>-29.039</X><Y>45.331</Y></End></Segment>
		<Segment><SegStyle>4</SegStyle><End><X>-29.810</X><Y>42.957</Y></End></Segment>
		<Segment><SegStyle>6</SegStyle><End><X>-29.810</X><Y>43.248</Y></End></Segment>
		<Segment><SegStyle>4</SegStyle><End><X>-29.133</X><Y>45.331</Y></End></Segment>
		<Segment><SegStyle>6</SegStyle><End><X>-29.228</X><Y>45.331</Y></End></Segment>
		<Segment><SegStyle>4</SegStyle><End><X>-29.810</X><Y>43.539</Y></End></Segment>
		<Segment><SegStyle>6</SegStyle><End><X>-29.810</X><Y>43.830</Y></End></Segment>
		<Segment><SegStyle>4</SegStyle><End><X>-29.322</X><Y>45.331</Y></End></Segment>
		<Segment><SegStyle>6</SegStyle><End><X>-29.417</X><Y>45.331</Y></End></Segment>
		<Segment><SegStyle>4</SegStyle><End><X>-29.810</X><Y>44.122</Y></End></Segment>
		<Segment><SegStyle>6</SegStyle><End><X>-29.810</X><Y>44.413</Y></End></Segment>
		<Segment><SegStyle>4</SegStyle><End><X>-29.512</X><Y>45.331</Y></End></Segment>
		<Segment><SegStyle>6</SegStyle><End><X>-29.606</X><Y>45.331</Y></End></Segment>
		<Segment><SegStyle>4</SegStyle><End><X>-29.810</X><Y>44.704</Y></End></Segment>
		<Segment><SegStyle>6</SegStyle><End><X>-29.810</X><Y>44.995</Y></End></Segment>
		<Segment><SegStyle>4</SegStyle><End><X>-29.701</X><Y>45.331</Y></End></Segment>
		<Segment><SegStyle>6</SegStyle><End><X>-29.796</X><Y>45.331</Y></End></Segment>
		<Segment><SegStyle>4</SegStyle><End><X>-29.810</X><Y>45.287</Y></End></Segment></Path></Trajectory></TrajectoryList></Layer>